Workbook
Name _30_Jun_13: [1]ESTIMATES!$A$4
Name current_price: [2]KeyData!$B$13
Name dcf_discount: DCF!$B$5
Name dcf_mos: '[2]DCF Valuation'!$E$3
Name Estiamtes: #REF!
Name ESTIMATES: [1]ESTIMATES!$A$1
Name FCFE_growth: [2]DCFData!$H$81
Name FCFF_growth: [2]DCFData!$H$82
Name graham_eps: #REF!
Name list_discount: [2]Lists!$E$2:$E$7
Name list_graham_sensitivity: [2]Lists!$M$2:$M$5
Name list_terminal: [2]Lists!$G$2:$G$9
Name user_discount: DCF!$B$6
Name user_fcf: DCF!$E$5
Name user_graham_growth: #REF!
Name user_growth: DCF!$G$5
Name WACC: WACC!$C$40

Sheet Company Profile
A1: Address | B1: Kelvin Road North/Cripps Road, Graniteside, Box GT942
B2: Harare, Zimbabwe
A3: Industry | B3: Electronic & Electrical Equipment
A5: Sector | B5: Industrials
A7: Senior Management | B7: HILTION MACKLIN
B8: Manging Director
B9: MARTIN GURIRA
B10: Operations Director & Group Secretary
A14: Company description | B14: Powerspeed Electrical is a leading supplier of electrical, hardware, building and home improvement products and services; trading through its own chain of hardware retail outlets known as Electrosales Hardware. The company supplies electrical products and solutions to the painting, plumbing, electrical, building, hand and power tools, outdoor and gardening, and automotive industries in Zimbabwe.

Sheet Financials HY
B1: June | C1: June | D1: June | E1: June | F1: June | G1: June | H1: June | I1: June
B2: 2017 | C2: 2018 | D2: 2019 | E2: 2020 | F2: 2021 | G2: 2022 | H2: 2023 | I2: 2024
A3: Revenue | C3: 17948319 | D3: 320682914 | E3: 1376518853 | F3: =6321175173 -> 6321175173 | G3: 47635606205 | H3: 24148941 | I3: 31510454
A4: Cost of sales
A5: Gross Profit
A6: Operating expenses
A7: Other operating income
A8: Other expenses
A9: EBITDA | C9: 914453 | D9: 85393209 | E9: 826342145 | F9: 1714448051 | G9: 14118589191 | H9: 2637174 | I9: 7269383
A10: Other income | C10: 202041 | D10: 0 | E10: 0 | F10: 0 | G10: 0 | H10: 0 | I10: 0
A11: Fair value adjustments | D11: 57971722 | G11: 12044759748 | H11: 0 | I11: 0
A12: Depreciation | D12: -16562305 | E12: -83442834 | F12: -233337964 | G12: -1375215691 | H12: -740093 | I12: -2232633
A13: EBIT | C13: 690502 | D13: =SUM(D9:D12) -> 126802626 | E13: =SUM(E9:E12) -> 742899311 | F13: =SUM(F9:F12) -> 1481110087 | G13: =SUM(G9:G12) -> 24788133248 | H13: =SUM(H9:H12) -> 1897081 | I13: =SUM(I9:I12) -> 5036750
A14: Reclassfication of foreign currency translation reserve
A15: Fair value adjustments | E15: 93397843 | H15: 2200
A16: Net monetory gain | E16: -468751991 | F16: -154275369 | G16: 1861396121 | H16: 2801682 | I16: 0
A17: Finance costs | C17: -90061 | D17: -795237 | E17: -3222233 | F17: -59927147 | G17: -379053344 | H17: -120697 | I17: -158659
A18: Income Before Tax (EBT) | C18: =SUM(C13:C17) -> 600441 | D18: =SUM(D13:D17) -> 126007389 | E18: =SUM(E13:E17) -> 364322930 | F18: =SUM(F13:F17) -> 1266907571 | G18: =SUM(G13:G17) -> 26270476025 | H18: =SUM(H13:H17) -> 4580266 | I18: =SUM(I13:I17) -> 4878091
A19: Tax | C19: -67842 | D19: -6122882 | E19: -111410791 | F19: -415479238 | G19: -3889336867 | H19: -1132242 | I19: -1253687
A20: Profit from continuing operations | C20: =SUM(C18:C19) -> 532599 | D20: =SUM(D18:D19) -> 119884507 | E20: =SUM(E18:E19) -> 252912139 | F20: =SUM(F18:F19) -> 851428333 | G20: =SUM(G18:G19) -> 22381139158 | H20: =SUM(H18:H19) -> 3448024 | I20: =SUM(I18:I19) -> 3624404
A21: Tax rate | C21: =C19/C18 -> -0.11298695 | D21: =D19/D18 -> -0.048591452 | E21: =E19/E18 -> -0.3058023 | F21: =F19/F18 -> -0.32794755 | G21: =G19/G18 -> -0.14804973 | H21: =-H19/H18 -> 0.24720005 | I21: =-I19/I18 -> 0.25700361
A23: BALANCE SHEET | C23: =C1 -> June | D23: =D1 -> June | E23: =E1 -> June | F23: =F1 -> June | G23: =G1 -> June | H23: =H1 -> June | I23: =I1 -> June
C24: =C2 -> 2018 | D24: =D2 -> 2019 | E24: =E2 -> 2020 | F24: =F2 -> 2021 | G24: =G2 -> 2022 | H24: =H2 -> 2023 | I24: =I2 -> 2024
A25: PPE | C25: 8691388 | D25: 442451689 | E25: 1185122316 | F25: 4719400769 | G25: 57875390570 | H25: 23630406 | I25: 21568656
A26: Deferred tax asset
A27: Investment in Property | C27: 4616000 | D27: 171367608 | E27: 487211857 | F27: 3133405427 | G27: 28444264032 | H27: 7800930 | I27: 7800930
A28: Intangible asset
A29: Investments | C29: 2795681 | D29: 31321964 | E29: 195797383 | F29: 326985199 | G29: 624049792 | H29: 78304 | I29: 44688
A30: Total Non current Assets | C30: =SUM(C25:C29) -> 16103069 | D30: =SUM(D25:D29) -> 645141261 | E30: =SUM(E25:E29) -> 1868131556 | F30: =SUM(F25:F29) -> 8179791395 | G30: =SUM(G25:G29) -> 86943704394 | H30: =SUM(H25:H29) -> 31509640 | I30: =SUM(I25:I29) -> 29414274
A31: Current Assets
A32: Inventories | C32: 1725984 | D32: 75162374 | E32: 142152818 | F32: 406327543 | G32: 1473577727 | H32: 4580974 | I32: 4454927
A33: Prepayment and deposits
A34: Trade and other receivables
A35: Contracts in progress and contracts receivables | C35: 20357440 | D35: 451781602 | E35: 3299646475 | F35: 12524656727 | G35: 90769319905 | H35: 46962352 | I35: 43607531
A36: Short term investments
A37: Tax Assets | C37: 78579 | D37: 0 | E37: 0 | F37: 0 | G37: 0 | H37: 0 | I37: 0
A38: Cash and equivalents | C38: 3788881 | D38: 30982916 | E38: 287137113 | F38: 3851755397 | G38: 4463107397 | H38: 2731700 | I38: 2165459
A39: Assets classified as held for sale
A40: Loans
A41: Total Current Assets | C41: =SUM(C32:C40) -> 25950884 | D41: =SUM(D32:D40) -> 557926892 | E41: =SUM(E32:E40) -> 3728936406 | F41: =SUM(F32:F40) -> 16782739667 | G41: =SUM(G32:G40) -> 96706005029 | H41: =SUM(H32:H40) -> 54275026 | I41: =SUM(I32:I40) -> 50227917
A42: Assets in disposal group as held for sale
A43: Total Assets | C43: =C41+C30 -> 42053953 | D43: =D41+D30 -> 1203068153 | E43: =E41+E30 -> 5597067962 | F43: =F41+F30 -> 24962531062 | G43: =G41+G30 -> 183649709423 | H43: =H41+H30 -> 85784666 | I43: =I41+I30 -> 79642191
A44: Equity and Liabilities
A45: Share Capital | C45: 2331824 | D45: 38175761 | E45: 78887924 | F45: 230011052 | G45: 1126983957 | H45: 2316175 | I45: 2316175
A46: Share Premium | C46: 405428 | D46: 14369668 | E46: 29694059 | F46: 86578038 | G46: 424205957 | H46: 455177 | I46: 455177
A47: Non distributable reserve | C47: 10232276 | D47: 473739337 | E47: 1188919749 | F47: 3127406954 | G47: 30781384457 | H47: 7426896 | I47: 7393616
A48: Revaluation reserve
A49: Foreign currency translation reserve
A50: Equity component of shareholders loans
A51: Retained earnings | C51: 3579150 | D51: 152795182 | E51: 710858124 | F51: 3911463129 | G51: 54504859077 | H51: 14028887 | I51: 17653291
A52: Equity attributable to equity holders of the parent | C52: =SUM(C45:C51) -> 16548678 | D52: =SUM(D45:D51) -> 679079948 | E52: =SUM(E45:E51) -> 2008359856 | F52: =SUM(F45:F51) -> 7355459173 | G52: =SUM(G45:G51) -> 86837433448 | H52: =SUM(H45:H51) -> 24227135 | I52: =SUM(I45:I51) -> 27818259
A53: Non-controlling interest
A54: Total Equity | C54: =C52+C53 -> 16548678 | D54: =D52+D53 -> 679079948 | E54: =E52+E53 -> 2008359856 | F54: =F52+F53 -> 7355459173 | G54: =G52+G53 -> 86837433448 | H54: =H52+H53 -> 24227135 | I54: =I52+I53 -> 27818259
A56: Deferred tax liability | C56: 2312928 | D56: 144495370 | E56: 378505523 | F56: 1929050552 | G56: 21928416419 | H56: 7861646 | I56: 9106460
A57: Long term payable
A58: Finance lease liabilities | C58: 414796 | D58: 656090
A59: Interest bearing borrowings | C59: 200000 | D59: 6022068 | E59: 30318524
A60: Non current Liabilities | C60: =SUM(C56:C59) -> 2927724 | D60: =SUM(D56:D59) -> 151173528 | E60: =SUM(E56:E59) -> 408824047 | F60: =SUM(F56:F59) -> 1929050552 | G60: =SUM(G56:G59) -> 21928416419 | H60: 7861646 | I60: =SUM(I56:I59) -> 9106460
A61: Current Liabilities
A62: Provisions
A63: Deferred consideration
A64: Interest bearing borrowings | C64: 644857 | D64: 5195650 | E64: 125658532 | F64: 725271918 | G64: 1323713920 | H64: 1880547 | I64: 1265615
A65: Trade and other payables | C65: 21419875 | D65: 367141607 | E65: 3054175234 | F65: 14952749419 | G65: 73560145636 | H65: 51815338 | I65: 41451857
A66: Finance lease liabilities | C66: 512910 | D66: 477420 | E66: 50293
A67: Subscontractors
A68: Liabilities directly associated with assets in disposal group
A69: Total Current liabilities | C69: =SUM(C61:C67) -> 22577642 | D69: =SUM(D61:D67) -> 372814677 | E69: =SUM(E61:E67) -> 3179884059 | F69: =SUM(F61:F67) -> 15678021337 | G69: =SUM(G61:G67) -> 74883859556 | H69: =SUM(H61:H67) -> 53695885 | I69: =SUM(I61:I67) -> 42717472
A70: Total Liabilities | C70: =C69+C60 -> 25505366 | D70: =D69+D60 -> 523988205 | E70: =E69+E60 -> 3588708106 | F70: =F69+F60 -> 17607071889 | G70: =G69+G60 -> 96812275975 | H70: =H69+H60 -> 61557531 | I70: =I69+I60 -> 51823932
A71: TOTAL LIABILITIES and EQUITY | C71: =C70+C54 -> 42054044 | D71: =D70+D54 -> 1203068153 | E71: =E70+E54 -> 5597067962 | F71: =F70+F54 -> 24962531062 | G71: =G70+G54 -> 183649709423 | H71: =H70+H54 -> 85784666 | I71: =I70+I54 -> 79642191
A72: Invested Capital | C72: =C64+C66+C59+C58+C54-C38 -> 14532360 | D72: =D64+D66+D59+D58+D54-D38 -> 660448260 | E72: =E64+E66+E59+E58+E54-E38 -> 1877250092 | F72: =F64+F66+F59+F58+F54-F38 -> 4228975694 | G72: =G64+G66+G59+G58+G54-G38 -> 83698039971 | H72: =H64+H66+H59+H58+H54-H38 -> 23375982 | I72: =I64+I66+I59+I58+I54-I38 -> 26918415
A74: ROIC | B74: =B13*(1-B21)/B72*2 -> #DIV/0! | C74: =C13*(1-C21)/C72*2 -> 0.10576668 | D74: =D13*(1-D21)/D72*2 -> 0.40264819 | E74: =E13*(1-E21)/E72*2 -> 1.0335113 | F74: =F13*(1-F21)/F72*2 -> 0.93017159 | G74: =G13*(1-G21)/G72*2 -> 0.68001616 | H74: =H13*(1-H21)/H72*2 -> 0.12218716 | I74: =I13*(1-I21)/I72*2 -> 0.27804661
A75: Market Cap | E75: =E77*E76/100 -> 2.4648678e+08 | F75: =F77*F76/100 -> 9.670933e+09 | G75: =G77*G76/100 -> 12082685350 | H75: =H77*H76/100 -> 1.9448049e+11 | I75: =I76*I77 -> 22232141 | J75: =I75/I77 -> 0.092
A76: Share price | E76: 102 | F76: 4001.98 | G76: 5000 | H76: 80479 | I76: =(230/100)/25 -> 0.092
A77: Share issued | E77: 241653707 | F77: 241653707 | G77: 241653707 | H77: 241653707 | I77: 241653707
A78: Net cash per share | D78: =(D38-D59-D64)/D77*100 -> #DIV/0! | E78: =(E38-E59-E64)/E77*100 -> 54.276038 | F78: =(F38-F59-F64)/F77*100 -> 1293.7867 | G78: =(G38-G59-G64)/G77*100 -> 1299.129 | H78: =(H38-H59-H64)/H77*100 -> 0.35222013 | I78: =(I38-I59-I64)/I77*100 -> 0.37236921
A81: Capex | D81: -345727700 | E81: -44630616 | F81: -114000000 | G81: 1400000000 | H81: -823592 | I81: -174173
A82: Depreciation | D82: 40379991 | E82: 40379991 | F82: =-F12 -> 233337964 | G82: =-G12 -> 1375215691 | H82: =-H12 -> 740093 | I82: =-I12 -> 2232633
A83: Non cash working capital | E83: =98069623-135895284+34409429 -> -3416232 | F83: =-(F32-E32)-(F35-E35)+(F65-E65) -> 2409389208 | G83: =-(G32-F32)-(G35-F35)+(G65-F65) -> -20704517145 | H83: =-(H32-G32)-(H35-G35)+(H65-G65) -> 18683024008 | I83: =-(I32-H32)-(I35-H35)+(I65-H65) -> -6882613
A84: Reinvestment | E84: =E81+E82+E83 -> -7666857 | F84: =F82+F81+F83 -> 2528727172 | G84: =G82+G81+G83 -> -17929301454 | H84: =H82+H81+H83 -> 18682940509 | I84: =I82+I81+I83 -> -4824153
A85: Reinvestment/Sales | E85: =E84/E3 -> -0.0055697435 | F85: =F84/F3 -> 0.40004067 | G85: =G84/G3 -> -0.37638445 | H85: =H84/H3 -> 773.65465 | I85: =I84/I3 -> -0.15309691

Sheet Quarters
D2: 2018 | E2: Q2 | F2: Q3
C3: Revenue | D3: ='Financials FY'!L3 -> 248549590 | E3: ='Financials HY'!D3 -> 320682914 | F3: 76389003 | J3: 17948319 | K3: =(D3-J3)/2 -> 1.1530064e+08 | L3: =K3+J3 -> 1.3324895e+08 | M3: =(F3-L3)/L3 -> -0.42671968
C4: EBITDA | F4: 19097251
C5: EBIT
C6: EbitMargin | F6: =F4/F3 -> 0.25

Sheet Data Input
A1: OTHER COMPANIES | B1: FY2012 | C1: FY2013 | D1: FY2014 | E1: FY2015 | F1: FY2016 | G1: FY2017 | H1: FY2018 | I1: FY2019 | J1: FY2020 | K1: FY2021 | L1: FY2022 | M1: FY2023 | N1: FY2024F
P2: RATINGS BACKGROUND CALCULATIONS | S2: Share PRICE PROFILE METRICS
A3: intangible assets | D3: ='Financials FY'!H45 -> 0 | E3: ='Financials FY'!I45 -> 0 | F3: ='Financials FY'!J45 -> 0 | G3: ='Financials FY'!K42 -> 8727868 | H3: ='Financials FY'!L42 -> 53986552 | I3: ='Financials FY'!M42 -> 757571799 | J3: ='Financials FY'!N42 -> 1578414353 | K3: ='Financials FY'!O42 -> 7410742000 | L3: ='Financials FY'!P42 -> 19944208 | M3: ='Financials FY'!Q42 -> 23630406
A4: Adjusted book value | C4: ='Financials FY'!G71 -> 0 | D4: ='Financials FY'!H71 -> 20112053 | E4: ='Financials FY'!I71 -> 11790662 | F4: ='Financials FY'!J71 -> 12311543 | G4: ='Financials FY'!K71 -> 14038405 | H4: ='Financials FY'!L71 -> 102795573 | I4: ='Financials FY'!M71 -> 1162729925 | J4: ='Financials FY'!N71 -> 2674849654 | ... M4: ='Financials FY'!Q71 -> 24227135 | S4: Price | T4: =M12 -> 11
A5: Interest expense | C5: =-('Financials FY'!G13+'Financials FY'!G16) -> 0 | D5: =-('Financials FY'!H13+'Financials FY'!H16) -> 344253 | E5: =-('Financials FY'!I13+'Financials FY'!I16) -> 82569 | F5: =-('Financials FY'!J13+'Financials FY'!J16) -> 39621 | G5: =-('Financials FY'!K13+'Financials FY'!K16) -> 117448 | H5: =-('Financials FY'!L13+'Financials FY'!L16) -> 1070216 | I5: =-('Financials FY'!M13+'Financials FY'!M16) -> 4265353 | J5: =-('Financials FY'!N13+'Financials FY'!N16) -> 12987289 | ... M5: =-('Financials FY'!Q13+'Financials FY'!Q16) -> 363607 | P5: DCF | Q5: =M9 -> 1.0869176 | S5: Change from previous day | T5: =T4-T7 -> 11
A6: Capex | C6: =-'Financials FY'!G121 -> 0 | D6: =-'Financials FY'!H121 -> 0 | E6: =-'Financials FY'!I121 -> 135586 | F6: =-'Financials FY'!J121 -> 1765204 | G6: =-'Financials FY'!K121 -> 2920223 | H6: =-'Financials FY'!L121 -> 1633551 | I6: =-'Financials FY'!M121 -> 589737378 | J6: =-'Financials FY'!N121 -> 492532971 | ... M6: =-'Financials FY'!Q121 -> 4150995 | P6: Price | Q6: =M12 -> 11 | S6: Percentage change (%) | T6: =T5/T7 -> #DIV/0!
A7: Gross profit | C7: ='Financials FY'!G5 -> 0 | D7: ='Financials FY'!H5 -> 14848743 | E7: ='Financials FY'!I5 -> 10039549 | F7: ='Financials FY'!J5 -> 19139918 | G7: ='Financials FY'!K5 -> 4197192 | H7: ='Financials FY'!L5 -> 0 | I7: ='Financials FY'!M5 -> 1498657461 | J7: ='Financials FY'!N5 -> 8390738256 | ... M7: ='Financials FY'!Q5 -> 53834005 | P7: Price/Earnings Ratio (P/E) | Q7: =(M12*M18/(100*M15)) -> 3.4875833 | S7: Prev Close | T7: =M13 -> 0
P8: P/E (Forward) | Q8: =(M12*M18/(100*N14)) -> 3.4875833 | S8: 52 Week Range
A9: DCF | E9: =F9 -> 1.0869176 | F9: =G9 -> 1.0869176 | G9: =I9 -> 1.0869176 | H9: =K9 -> 0 | I9: =M9 -> 1.0869176 | J9: =N9 -> 9.0470364 | K9: =O9 -> 0 | L9: =P9 -> Price/NAV | M9: =Q9 -> 1.0869176 | N9: =DCF!C40 -> 9.0470364 | P9: Price/NAV | Q9: =(M12*M18)/((M17))/100 -> 1.0869176 | S9: PE Ratio | T9: =Q7 -> 3.4875833
A10: Earnings before interest and tax (EBIT) | C10: ='Financials FY'!G10 -> 0 | D10: ='Financials FY'!H10 -> -936437 | E10: ='Financials FY'!I10 -> -1354722 | F10: ='Financials FY'!J10 -> -2685172 | G10: ='Financials FY'!K10 -> -2946075 | H10: ='Financials FY'!L10 -> 11596451 | I10: ='Financials FY'!M10 -> 402731168 | J10: ='Financials FY'!N10 -> 1567387720 | ... M10: ='Financials FY'!Q10 -> 8237104 | N10: =M10*(1+DCF!L13) -> 8237104 | P10: EV/EBIT | Q10: =M36/M10 -> 2.5897812 | S10: Forward PE: | T10: =Q8 -> 3.4875833
P11: P/OP cashflow | Q11: =(M12*M18/(100*M23)) -> 5.28917 | S11: ROE | T11: =Q25 -> 0.31165352
A12: Share Price (cents) | D12: ='Financials FY'!H130 -> 0 | E12: ='Financials FY'!I130 -> 0.81 | F12: ='Financials FY'!J130 -> 1.7 | G12: ='Financials FY'!K130 -> 7.2 | H12: ='Financials FY'!L130 -> 7.56 | I12: ='Financials FY'!M130 -> 48 | J12: ='Financials FY'!N130 -> 4001.38 | K12: ='Financials FY'!O130 -> 7000 | ... M12: ='Financials FY'!Q130 -> 11 | P12: Net profit growth | Q12: =(M15-I15)/I15 -> -0.95091717 | S12: ROA | T12: =Q26 -> 0.092055552
A13: Share price (previous day closing price) | P13: Net profit growth (F) | Q13: =(N15-M15)/M15 -> 0 | S13: EPS | T13: =Q18*100 -> 3.1540465
A14: Earnings attributable for shareholders | C14: ='Financials FY'!G25 -> 0 | D14: ='Financials FY'!H25 -> -1033304 | E14: ='Financials FY'!I25 -> -834961 | F14: ='Financials FY'!J25 -> -2804842 | G14: ='Financials FY'!K25 -> -3498454 | H14: ='Financials FY'!L25 -> 9167385 | I14: ='Financials FY'!M25 -> 153831213 | J14: ='Financials FY'!N25 -> 526238344 | ... M14: ='Financials FY'!Q25 -> 7550472 | N14: =M14*(1+DCF!L13) -> 7550472 | P14: Cash generated from operations growth | Q14: =(M23-I23)/I23 -> -0.99155727 | S14: P/NAV | T14: =Q9 -> 1.0869176
A15: Net profit | C15: ='Financials FY'!G19 -> 0 | D15: ='Financials FY'!H19 -> -1033304 | E15: ='Financials FY'!I19 -> -834961 | F15: ='Financials FY'!J19 -> -2804842 | G15: ='Financials FY'!K19 -> -3498454 | H15: ='Financials FY'!L19 -> 9167385 | I15: ='Financials FY'!M19 -> 153831213 | J15: ='Financials FY'!N19 -> 526238344 | ... M15: ='Financials FY'!Q19 -> 7550472 | N15: =M15*(1+DCF!L13) -> 7550472 | S15: DCF | T15: =DCF!C38 -> 21657700
A16: Revenue | D16: ='Financials FY'!H3 -> 14848743 | E16: ='Financials FY'!I3 -> 10039549 | F16: ='Financials FY'!J3 -> 19139918 | G16: ='Financials FY'!K3 -> 27451196 | H16: ='Financials FY'!L3 -> 248549590 | I16: ='Financials FY'!M3 -> 1498657461 | J16: ='Financials FY'!N3 -> 8390738256 | K16: ='Financials FY'!O3 -> 25284481000 | ... M16: ='Financials FY'!Q3 -> 53834005 | N16: =DCF!B16 -> 57112496 | P16: Revenue growth | Q16: =(M16-I16)/I16 -> -0.96407851 | S16: Market Cap | T16: =Q24 -> 26332900
A17: Equity | C17: ='Financials FY'!G71 -> 0 | D17: ='Financials FY'!H71 -> 20112053 | E17: ='Financials FY'!I71 -> 11790662 | F17: ='Financials FY'!J71 -> 12311543 | G17: ='Financials FY'!K71 -> 14038405 | H17: ='Financials FY'!L71 -> 102795573 | I17: ='Financials FY'!M71 -> 1162729925 | J17: ='Financials FY'!N71 -> 2674849654 | ... M17: ='Financials FY'!Q71 -> 24227135 | P17: Revenue growth (F) | Q17: =(N16-M16)/M16 -> 0.0609 | S17: NAV | T17: =M38 -> 27818259
A18: Issued Shares | D18: ='Financials FY'!H131 -> 0 | E18: ='Financials FY'!I131 -> 220493732 | F18: ='Financials FY'!J131 -> 220493732 | G18: ='Financials FY'!K131 -> 232019894 | H18: ='Financials FY'!L131 -> 233182394 | I18: ='Financials FY'!M131 -> 241653707 | J18: ='Financials FY'!N131 -> 241653707 | K18: ='Financials FY'!O131 -> 241653707 | ... M18: ='Financials FY'!Q131 -> 239390000 | P18: EPS | Q18: =M14/M18 -> 0.031540465 | S18: Issued Shares | T18: =M18 -> 239390000
A19: Cash and bank balances | D19: ='Financials FY'!H55 -> 1729139 | E19: ='Financials FY'!I55 -> 737173 | F19: ='Financials FY'!J55 -> 780267 | G19: ='Financials FY'!K55 -> 1294967 | H19: ='Financials FY'!L55 -> 23534630 | I19: ='Financials FY'!M55 -> 53049371 | J19: ='Financials FY'!N55 -> 382425791 | K19: ='Financials FY'!O55 -> 6048304000 | ... M19: ='Financials FY'!Q55 -> 2731700 | P19: EBIT growth | Q19: =(M10-K10)/K10 -> -0.99823368 | S19: NB: all per share metrics are in cents
A20: Minority interest | D20: ='Financials FY'!H70 -> 0 | E20: ='Financials FY'!I70 -> 0 | F20: ='Financials FY'!J70 -> 0 | G20: ='Financials FY'!K70 -> 0 | H20: ='Financials FY'!L70 -> 0 | I20: ='Financials FY'!M70 -> 0 | J20: ='Financials FY'!N70 -> 0 | K20: ='Financials FY'!O70 -> 0 | ... M20: ='Financials FY'!Q70 -> 0 | P20: EBIT growth (F) | Q20: =(N10-M10)/M10 -> 0
A21: Preferred shares | P21: FCF growth | Q21: =(M33-I33)/I33 -> -21.147274 | S21: FINANCIALS SUMMARY
A22: Net Operating cashflow | D22: ='Financials FY'!H97 -> 1969797 | E22: ='Financials FY'!I97 -> 1969797 | F22: ='Financials FY'!J97 -> 591511 | G22: ='Financials FY'!K97 -> 2265802 | H22: ='Financials FY'!L97 -> 20072981 | I22: ='Financials FY'!M97 -> 589696298 | J22: ='Financials FY'!N97 -> 615874311 | K22: ='Financials FY'!O97 -> 8721813000 | ... M22: ='Financials FY'!Q97 -> 4978645 | S22: INCOME STATEMENT | T22: =F1 -> FY2016 | U22: =G1 -> FY2017 | V22: =H1 -> FY2018 | W22: =I1 -> FY2019 | X22: =J1 -> FY2020 | Y22: =K1 -> FY2021 | Z22: =L1 -> FY2022 | AA22: =M1 -> FY2023
A23: Cash generated from operations | C23: ='Financials FY'!G92 -> 0 | D23: ='Financials FY'!H92 -> 1969797 | E23: ='Financials FY'!I92 -> 1633461 | F23: ='Financials FY'!J92 -> 553165 | G23: ='Financials FY'!K92 -> 2383250 | H23: ='Financials FY'!L92 -> 20072981 | I23: ='Financials FY'!M92 -> 589696298 | J23: ='Financials FY'!N92 -> 615874311 | ... M23: ='Financials FY'!Q92 -> 4978645 | P23: Net cash inflow from operations per share | Q23: =M22/M18*100 -> 2.0797214 | S23: Revenue | T23: =F16 -> 19139918 | U23: =G16 -> 27451196 | V23: =H16 -> 248549590 | W23: =I16 -> 1498657461 | X23: =J16 -> 8390738256 | Y23: =K16 -> 25284481000 | Z23: =L16 -> 49818414 | AA23: =M16 -> 53834005
A24: Current assets | D24: ='Financials FY'!H58 -> 17418677 | E24: ='Financials FY'!I58 -> 9874579 | F24: ='Financials FY'!J58 -> 11924380 | G24: ='Financials FY'!K58 -> 17666048 | H24: ='Financials FY'!L58 -> 161193886 | I24: ='Financials FY'!M58 -> 955290015 | J24: ='Financials FY'!N58 -> 4966412877 | K24: ='Financials FY'!O58 -> 26353465000 | ... M24: ='Financials FY'!Q58 -> 54275026 | P24: Market Capitalisation | Q24: =M18*M12/100 -> 26332900 | S24: Gross Profit | T24: =F7 -> 19139918 | U24: =G7 -> 4197192 | V24: =H7 -> 0 | W24: =I7 -> 1498657461 | X24: =J7 -> 8390738256 | Y24: =K7 -> 25284481000 | Z24: =L7 -> 49818414 | AA24: =M7 -> 53834005
A25: Current liabilities | D25: ='Financials FY'!H86 -> 11033528 | E25: ='Financials FY'!I86 -> 7967258 | F25: ='Financials FY'!J86 -> 10564576 | G25: ='Financials FY'!K86 -> 15929669 | H25: ='Financials FY'!L86 -> 140240986 | I25: ='Financials FY'!M86 -> 638338362 | J25: ='Financials FY'!N86 -> 4235153252 | K25: ='Financials FY'!O86 -> 24618756000 | ... M25: ='Financials FY'!Q86 -> 53695885 | P25: ROE | Q25: =M14/M17 -> 0.31165352 | S25: EBIT | T25: =F10 -> -2685172 | U25: =G10 -> -2946075 | V25: =H10 -> 11596451 | W25: =I10 -> 402731168 | X25: =J10 -> 1567387720 | Y25: =K10 -> 4663423000 | Z25: =L10 -> 12367050 | AA25: =M10 -> 8237104
A26: Non current liabilities | C26: ='Financials FY'!G77 -> 0 | D26: ='Financials FY'!H77 -> 2823600 | E26: ='Financials FY'!I77 -> 1286033 | F26: ='Financials FY'!J77 -> 1566298 | G26: ='Financials FY'!K77 -> 3188102 | H26: ='Financials FY'!L77 -> 18181525 | I26: ='Financials FY'!M77 -> 258841370 | J26: ='Financials FY'!N77 -> 544495477 | ... M26: ='Financials FY'!Q77 -> 7861646 | P26: ROA | Q26: =M10*(1-M37)/(M32+M24) -> 0.092055552 | S26: Net Profit | T26: =F15 -> -2804842 | U26: =G15 -> -3498454 | V26: =H15 -> 9167385 | W26: =I15 -> 153831213 | X26: =J15 -> 526238344 | Y26: =K15 -> 3386459000 | Z26: =L15 -> 12400715 | AA26: =M15 -> 7550472
A27: Trade Receivables | D27: ='Financials FY'!H51 -> 0 | E27: ='Financials FY'!I51 -> 1957829 | F27: ='Financials FY'!J51 -> 3579559 | G27: ='Financials FY'!K51 -> 5372084 | H27: ='Financials FY'!L51 -> 0 | I27: ='Financials FY'!M51 -> 0 | J27: ='Financials FY'!N51 -> 0 | K27: ='Financials FY'!O51 -> 0 | ... M27: ='Financials FY'!Q51 -> 0 | P27: ROIC | Q27: =(M10*(1-M37)/(M31+M30+M17-M34)) -> 0.33782345
A28: Cost of Sales | C28: =-'Financials FY'!G4 -> 0 | D28: =-'Financials FY'!H4 -> 0 | E28: =-'Financials FY'!I4 -> 0 | F28: =-'Financials FY'!J4 -> 0 | G28: =-'Financials FY'!K4 -> 23254004 | H28: =-'Financials FY'!L4 -> -248549590 | I28: =-'Financials FY'!M4 -> 0 | J28: =-'Financials FY'!N4 -> 0 | ... M28: =-'Financials FY'!Q4 -> 0 | P28: Net margin | Q28: =M15/M16 -> 0.1402547 | S28: CASHFLOW STATEMENT | T28: =T22 -> FY2016 | U28: =U22 -> FY2017 | V28: =V22 -> FY2018 | W28: =W22 -> FY2019 | X28: =X22 -> FY2020 | Y28: =Y22 -> FY2021 | Z28: =Z22 -> FY2022 | AA28: =AA22 -> FY2023
A29: Total Inventory | C29: ='Financials FY'!G49 -> 0 | D29: ='Financials FY'!H49 -> 5365107 | E29: ='Financials FY'!I49 -> 400472 | F29: ='Financials FY'!J49 -> 954819 | G29: ='Financials FY'!K49 -> 1200575 | H29: ='Financials FY'!L49 -> 10720948 | I29: ='Financials FY'!M49 -> 128694039 | J29: ='Financials FY'!N49 -> 189327333 | ... M29: ='Financials FY'!Q49 -> 4580974 | P29: Management | S29: Net cashflow from operations | T29: =F22 -> 591511 | U29: =G22 -> 2265802 | V29: =H22 -> 20072981 | W29: =I22 -> 589696298 | X29: =J22 -> 615874311 | Y29: =K22 -> 8721813000 | Z29: =L22 -> 771971 | AA29: =M22 -> 4978645
A30: Short term debt | D30: ='Financials FY'!H81+'Financials FY'!H83 -> 1166667 | E30: ='Financials FY'!I81+'Financials FY'!I83 -> 222267 | F30: ='Financials FY'!J81+'Financials FY'!J83 -> 390267 | G30: ='Financials FY'!K81+'Financials FY'!K83 -> 489995 | H30: ='Financials FY'!L81+'Financials FY'!L83 -> 7191467 | I30: ='Financials FY'!M81+'Financials FY'!M83 -> 9713506 | J30: ='Financials FY'!N81+'Financials FY'!N83 -> 167426274 | K30: ='Financials FY'!O81+'Financials FY'!O83 -> 1138874000 | ... M30: ='Financials FY'!Q81+'Financials FY'!Q83 -> 1880547 | P30: Receivables turnover % change | Q30: =((M16*2/(M27+I27))-(I16*2/(I27+M27)))/((I16*2/(I27+M27))) -> #DIV/0! | S30: Cash and cash equivalents | T30: =F19 -> 780267 | U30: =G19 -> 1294967 | V30: =H19 -> 23534630 | W30: =I19 -> 53049371 | X30: =J19 -> 382425791 | Y30: =K19 -> 6048304000 | Z30: =L19 -> 1538014 | AA30: =M19 -> 2731700
A31: Long term debt | C31: ='Financials FY'!G76+'Financials FY'!G75 -> 0 | D31: ='Financials FY'!H76+'Financials FY'!H75 -> 416667 | E31: ='Financials FY'!I76+'Financials FY'!I75 -> 222268 | F31: ='Financials FY'!J76+'Financials FY'!J75 -> 315567 | G31: ='Financials FY'!K76+'Financials FY'!K75 -> 1409130 | H31: ='Financials FY'!L76+'Financials FY'!L75 -> 3818246 | I31: ='Financials FY'!M76+'Financials FY'!M75 -> 11434433 | J31: ='Financials FY'!N76+'Financials FY'!N75 -> 40379961 | ... M31: ='Financials FY'!Q76+'Financials FY'!Q75 -> 0 | P31: Inventory turnover % change | Q31: =((I28*2/(I29+G29))-(G28*2/(G29+F29)))/(G28*2/(G29+F29)) -> -1 | S31: Free cashflow | T31: =F33 -> -1173693 | U31: =G33 -> -654421 | V31: =H33 -> 18439430 | W31: =I33 -> -41080 | X31: =J33 -> 123341340 | Y31: =K33 -> 4785081000 | Z31: =L33 -> -3974724 | AA31: =M33 -> 827650
A32: Non current assets | D32: ='Financials FY'!H47 -> 16550504 | E32: ='Financials FY'!I47 -> 11169374 | F32: ='Financials FY'!J47 -> 12518037 | G32: ='Financials FY'!K47 -> 15490128 | H32: ='Financials FY'!L47 -> 100024198 | I32: ='Financials FY'!M47 -> 1104619642 | J32: ='Financials FY'!N47 -> 2488085506 | K32: ='Financials FY'!O47 -> 12844496000 | ... M32: ='Financials FY'!Q47 -> 31509640 | P32: Debt ratio | Q32: =(M30+M31)/(M24+M32) -> 0.021921715 | S32: Capex | T32: =F6 -> 1765204 | U32: =G6 -> 2920223 | V32: =H6 -> 1633551 | W32: =I6 -> 589737378 | X32: =J6 -> 492532971 | Y32: =K6 -> 3936732000 | Z32: =L6 -> 4746695 | AA32: =M6 -> 4150995
A33: Free Cash Flow | D33: ='Financials FY'!H126 -> 1969797 | E33: ='Financials FY'!I126 -> 1834211 | F33: ='Financials FY'!J126 -> -1173693 | G33: ='Financials FY'!K126 -> -654421 | H33: ='Financials FY'!L126 -> 18439430 | I33: ='Financials FY'!M126 -> -41080 | J33: ='Financials FY'!N126 -> 123341340 | K33: ='Financials FY'!O126 -> 4785081000 | ... M33: ='Financials FY'!Q126 -> 827650 | P33: Total Asset Turnover % change | Q33: =((2*I16/(I32+I24+G24+G32))-(2*G16/(G32+G24+F24+F32)))/(2*G16/(G32+G24+F24+F32)) -> 0.50234645
A34: Cash balances | C34: ='Financials FY'!G55 -> 0 | D34: ='Financials FY'!H55 -> 1729139 | E34: ='Financials FY'!I55 -> 737173 | F34: ='Financials FY'!J55 -> 780267 | G34: ='Financials FY'!K55 -> 1294967 | H34: ='Financials FY'!L55 -> 23534630 | I34: ='Financials FY'!M55 -> 53049371 | J34: ='Financials FY'!N55 -> 382425791 | ... M34: ='Financials FY'!Q55 -> 2731700 | P34: Interest Cover ratio | Q34: =M10/M5 -> 22.653865 | S34: BALANCE SHEET | T34: =T28 -> FY2016 | U34: =U28 -> FY2017 | V34: =V28 -> FY2018 | W34: =W28 -> FY2019 | X34: =X28 -> FY2020 | Y34: =Y28 -> FY2021 | Z34: =Z28 -> FY2022 | AA34: =AA28 -> FY2023
A35: Dividend | D35: 0 | E35: 0 | F35: 0 | G35: 0 | H35: 1 | I35: 2 | J35: 3 | K35: 4 | L35: 5 | M35: 6 | P35: ST debt % of current assets | Q35: =M30/M24 -> 0.034648477 | S35: Non Current Assets | T35: =F32 -> 12518037 | U35: =G32 -> 15490128 | V35: =H32 -> 100024198 | W35: =I32 -> 1104619642 | X35: =J32 -> 2488085506 | Y35: =K32 -> 12844496000 | Z35: =L32 -> 29961324 | AA35: =M32 -> 31509640
A36: Enterprise value (EV) | D36: ='Financials FY'!H134+'Financials FY'!H81+'Financials FY'!H76-'Financials FY'!H55 -> -145805 | E36: ='Financials FY'!I134+'Financials FY'!I81+'Financials FY'!I76-'Financials FY'!I55 -> 1493361.2 | F36: ='Financials FY'!J134+'Financials FY'!J81+'Financials FY'!J76-'Financials FY'!J55 -> 3673960.4 | G36: ='Financials FY'!K134+'Financials FY'!K81+'Financials FY'!K76-'Financials FY'!K55 -> 16526318 | H36: ='Financials FY'!L134+'Financials FY'!L81+'Financials FY'!L76-'Financials FY'!L55 -> -658213.01 | I36: ='Financials FY'!M134+'Financials FY'!M81+'Financials FY'!M76-'Financials FY'!M55 -> 82151537 | J36: ='Financials FY'!N134+'Financials FY'!N81+'Financials FY'!N76-'Financials FY'!N55 -> 9.4947966e+09 | K36: ='Financials FY'!O134+'Financials FY'!O81+'Financials FY'!O76-'Financials FY'!O55 -> 12006329490 | L36: ='Financials FY'!P134+'Financials FY'!P81+'Financials FY'!P76-'Financials FY'!P55 -> 25500054 | M36: ='Financials HY'!I75+'Financials HY'!I64-'Financials HY'!I38 -> 21332297 | P36: Current ratio | Q36: =M24/M25 -> 1.0107856 | S36: Current Assets | T36: =F24 -> 11924380 | U36: =G24 -> 17666048 | V36: =H24 -> 161193886 | W36: =I24 -> 955290015 | X36: =J24 -> 4966412877 | Y36: =K24 -> 26353465000 | Z36: =L24 -> 33325474 | AA36: =M24 -> 54275026
A37: Tax Rate | D37: ='Financials FY'!H39 -> 0.71455246 | E37: ='Financials FY'!I39 -> 0.5277223 | F37: ='Financials FY'!J39 -> -0.072267647 | G37: ='Financials FY'!K39 -> -0.15727006 | H37: ='Financials FY'!L39 -> 0.12909174 | I37: ='Financials FY'!M39 -> 0.54310718 | J37: ='Financials FY'!N39 -> 0.093438368 | K37: ='Financials FY'!O39 -> 0.27168571 | ... M37: ='Financials FY'!Q39 -> 0.041294758 | P37: FCF/Debt | Q37: =M33/(M31+M30) -> 0.44011131 | S37: Intangible Assets | T37: =F3 -> 0 | U37: =G3 -> 8727868 | V37: =H3 -> 53986552 | W37: =I3 -> 757571799 | X37: =J3 -> 1578414353 | Y37: =K3 -> 7410742000 | Z37: =L3 -> 19944208 | AA37: =M3 -> 23630406
A38: Net book value | D38: ='Financials FY'!H71 -> 20112053 | E38: ='Financials FY'!I71 -> 11790662 | F38: ='Financials FY'!J71 -> 12311543 | G38: ='Financials FY'!K71 -> 14038405 | H38: ='Financials FY'!L71 -> 102795573 | I38: ='Financials FY'!M71 -> 1162729925 | J38: ='Financials FY'!N71 -> 2674849654 | K38: ='Financials FY'!O71 -> 11550071000 | L38: ='Financials FY'!P71 -> 29924703 | M38: ='Financials HY'!I54 -> 27818259 | P38: Gross Margin % change | Q38: =(M7/M16-I7/I16)/(I7/I16) -> 0 | S38: Short-term debt | T38: =F30 -> 390267 | U38: =G30 -> 489995 | V38: =H30 -> 7191467 | W38: =I30 -> 9713506 | X38: =J30 -> 167426274 | Y38: =K30 -> 1138874000 | Z38: =L30 -> 456160 | AA38: =M30 -> 1880547
A39: Invested Capital | C39: ='Financials FY'!G138 -> 0 | D39: ='Financials FY'!H138 -> 19966248 | E39: ='Financials FY'!I138 -> 11498024 | F39: ='Financials FY'!J138 -> 12237110 | G39: ='Financials FY'!K138 -> 14143433 | H39: ='Financials FY'!L138 -> 87694710 | I39: ='Financials FY'!M138 -> 1129705127 | J39: ='Financials FY'!N138 -> 2500230098 | ... M39: ='Financials FY'!Q138 -> 23375982 | P39: Gross Profit/Total Assets % change | Q39: =((I7/(I32+I24))-(G7/(G32+G24)))/(G7/(G32+G24)) -> 4.7472463 | S39: Long-term debt | T39: =F31 -> 315567 | U39: =G31 -> 1409130 | V39: =H31 -> 3818246 | W39: =I31 -> 11434433 | X39: =J31 -> 40379961 | Y39: =K31 -> 0 | Z39: =L31 -> 0 | AA39: =M31 -> 0
A40: EPS | E40: =E14/E18 -> -0.0037867788 | F40: =F14/F18 -> -0.012720733 | G40: =G14/G18 -> -0.01507825 | H40: =H14/H18 -> 0.039314225 | I40: =I14/I18 -> 0.63657709 | J40: =J14/J18 -> 2.1776548 | K40: =K14/K18 -> 14.013685 | L40: =L14/L18 -> 0.051316055 | M40: =M14/M18 -> 0.031540465 | P40: ROIC % change | Q40: =((M10*(1-M37)/M36)-(I10*(1-I37)/I36))/(I10*(1-I37)/I36) -> -0.83472463 | S40: Non Current Liabilities | T40: =F26 -> 1566298 | U40: =G26 -> 3188102 | V40: =H26 -> 18181525 | W40: =I26 -> 258841370 | X40: =J26 -> 544495477 | Y40: =K26 -> 3029134000 | Z40: =L26 -> 7556664 | AA40: =M26 -> 7861646
P41: Free cash flow yield | Q41: =M33/T16 -> 0.031430264 | S41: Current liabilities | T41: =F25 -> 10564576 | U41: =G25 -> 15929669 | V41: =H25 -> 140240986 | W41: =I25 -> 638338362 | X41: =J25 -> 4235153252 | Y41: =K25 -> 24618756000 | Z41: =L25 -> 25805431 | AA41: =M25 -> 53695885
A42: Order book | S42: Equity | T42: =F17 -> 12311543 | U42: =G17 -> 14038405 | V42: =H17 -> 102795573 | W42: =I17 -> 1162729925 | X42: =J17 -> 2674849654 | Y42: =K17 -> 11550071000 | Z42: =L17 -> 29924703 | AA42: =M17 -> 24227135
A44: Population | K44: 1970 | L44: 5000000
K45: 1980 | L45: 7000000 | M45: =L45-L44 -> 2000000 | N45: =M45/10 -> 200000 | S45: KEY RATIOS
K46: 1990 | L46: 10000000 | M46: =L46-L45 -> 3000000 | N46: =M46/10 -> 300000 | S46: KEY RATIOS | T46: =T34 -> FY2016 | U46: =U34 -> FY2017 | V46: =V34 -> FY2018 | W46: =W34 -> FY2019 | X46: =X34 -> FY2020 | Y46: =Y34 -> FY2021 | Z46: =Z34 -> FY2022 | AA46: =AA34 -> FY2023
K47: 2000 | L47: 12000000 | M47: =L47-L46 -> 2000000 | N47: =M47/10 -> 200000
K48: 2010 | L48: 13000000 | M48: =L48-L47 -> 1000000 | N48: =M48/10 -> 100000 | S48: EBIT Margins | T48: =F10/F16 -> -0.14029172 | U48: =G10/G16 -> -0.10732046 | V48: =H10/H16 -> 0.046656488 | W48: =I10/I16 -> 0.26872796 | X48: =J10/J16 -> 0.18679974 | Y48: =K10/K16 -> 0.18443815 | Z48: =L10/L16 -> 0.24824255 | AA48: =M10/M16 -> 0.15300931
K49: 2020 | L49: 16000000 | M49: =L49-L48 -> 3000000 | N49: =M49/10 -> 300000 | S49: Net profit margin | T49: =E15/E16 -> -0.083167182 | U49: =F15/F16 -> -0.1465441 | V49: =G15/G16 -> -0.12744268 | W49: =H15/H16 -> 0.036883525 | X49: =I15/I16 -> 0.10264601 | Y49: =J15/J16 -> 0.062716572 | Z49: =K15/K16 -> 0.13393429 | AA49: =M15/M16 -> 0.1402547
N50: =M50/10 -> 0 | S50: ROIC | T50: =F10*(1-F37)/F39 -> -0.2352862 | U50: =G10*(1-G37)/G39 -> -0.24105918 | V50: =H10*(1-H37)/H39 -> 0.11516595 | W50: =I10*(1-I37)/I39 -> 0.16287877 | X50: =J10*(1-J37)/J39 -> 0.56832112 | Y50: =K10*(1-K37)/K39 -> 0.51146232 | Z50: =L10*(1-L37)/L39 -> 0.40013096 | AA50: =M10*(1-M37)/M39 -> 0.33782345
M51: =(L49/L45)^(1/40)-1 -> 0.020882005 | S51: Debt Ratio | T51: =(F30+F31)/(F24+F32) -> 0.028877422 | U51: =(G30+G31)/(G24+G32) -> 0.057278167 | V51: =(H30+H31)/(H24+H32) -> 0.042147591 | W51: =(I30+I31)/(I24+I32) -> 0.01026644 | X51: =(J30+J31)/(J24+J32) -> 0.027876622 | Y51: =(K30+K31)/(K24+K32) -> 0.029054419 | Z51: =(L30+L31)/(L24+L32) -> 0.0072078224 | AA51: =(M30+M31)/(M24+M32) -> 0.021921715
M52: =(L49-L45)/L45 -> 1.2857143 | S52: Interest cover ratio | T52: =F10/F5 -> -67.771434 | U52: =G10/G5 -> -25.08408 | V52: =H10/H5 -> 10.835617 | W52: =I10/I5 -> 94.419188 | X52: =J10/J5 -> 120.68629 | Y52: =K10/K5 -> 13.764978 | Z52: =L10/L5 -> 50.351158 | AA52: =M10/M5 -> 22.653865
S53: Current ratio | T53: =F24/F25 -> 1.1287135 | U53: =G24/G25 -> 1.1090028 | V53: =H24/H25 -> 1.1494064 | W53: =I24/I25 -> 1.4965261 | X53: =J24/J25 -> 1.1726643 | Y53: =K24/K25 -> 1.0704629 | Z53: =L24/L25 -> 1.2914132 | AA53: =M24/M25 -> 1.0107856
M54: =365*10 -> 3650 | S54: Total Asset Turnover | T54: =2*F16/(F24+F32+E24+E32) -> 0.84156718 | U54: =2*G16/(G24+G32+F24+F32) -> 0.95318981 | V54: =2*H16/(H24+H32+G24+G32) -> 1.6886639 | W54: =2*I16/(I24+I32+H24+H32) -> 1.2913184 | X54: =2*J16/(J24+J32+I24+I32) -> 1.7637962 | Y54: =2*K16/(K24+K32+J24+J32) -> 1.0839506 | Z54: =2*L16/(L24+L32+K24+K32) -> 0.0025377907 | AA54: =2*M16/(M24+M32+L24+L32) -> 0.72225768
M55: =M49/M54 -> 821.91781 | S55: Price/Nav | T55: =F12*F18/F17 -> 30.446171 | U55: =G12*G18/G17 -> 118.99808 | V55: =H12*H18/H17 -> 17.149171 | W55: =I12*I18/I17 -> 9.9759864 | X55: =J12*J18/J17 -> 361.49632 | Y55: =K12*K18/K17 -> 146.45589 | Z55: =L12*L18/L17 -> 88.829312 | AA55: =M12*M18/M17 -> 108.69176
S56: EV/EBIT | T56: =F36/F10 -> -1.3682403 | U56: =G36/G10 -> -5.6096054 | V56: =H36/H10 -> -0.056759867 | W56: =I36/I10 -> 0.20398604 | X56: =J36/J10 -> 6.0577204 | Y56: =K36/K10 -> 2.5745744 | Z56: =L36/L10 -> 2.061935 | AA56: =M36/M10 -> 2.5897812
S57: Price/Op cashflow | T57: =F18*F12/F22 -> 633.69801 | U57: =G18*G12/G22 -> 737.28562 | V57: =H18*H12/H22 -> 87.822476 | W57: =I18*I12/I22 -> 19.670088 | X57: =J18*J12/J22 -> 1570.0416 | Y57: =K18*K12/K22 -> 193.94774 | Z57: =L18*L12/L22 -> 3443.3817 | AA57: =M18*M12/M22 -> 528.917

Sheet Financials FY
A1: INCOME STATEMENT | B1: Dec | C1: Dec | D1: Dec | E1: Dec | F1: Dec | G1: Dec | H1: Dec | I1: Dec | J1: Dec | K1: Dec | L1: Dec | M1: Dec | N1: Dec | O1: Dec | P1: Dec | Q1: Dec
A2: Turnover | B2: 2008 | C2: 2009 | D2: 2010 | E2: 2011 | F2: 2012 | G2: 2013 | H2: 2014 | I2: 2015 | J2: 2016 | K2: 2017 | L2: 2018 | M2: 2019 | N2: 2020 | O2: 2021 | P2: 2022 | Q2: 2023
A3: Revenue | H3: 14848743 | I3: 10039549 | J3: 19139918 | K3: 27451196 | L3: 248549590 | M3: 1498657461 | N3: 8390738256 | O3: 25284481000 | P3: =49818414 -> 49818414 | Q3: =53834005 -> 53834005
A4: Cost of sales | K4: -23254004 | L4: =L3-L5 -> 248549590
A5: Gross Profit | H5: =H3+H4 -> 14848743 | I5: =I3+I4 -> 10039549 | J5: =J3+J4 -> 19139918 | K5: =K3+K4 -> 4197192 | L5: =L3*P4 -> 0 | M5: =M3 -> 1498657461 | N5: =N3 -> 8390738256 | O5: =O3 -> 25284481000 | P5: =P3 -> 49818414 | Q5: =Q3 -> 53834005
A6: Profit before depriciation and fair value adjustments | H6: =244933 -> 244933 | I6: =245467 -> 245467 | L6: 20216067 | M6: 477331786 | N6: 1729386061 | O6: 5403401000 | P6: 14179147 | Q6: 12579230
A7: Depriciation | H7: =1156370 -> 1156370 | I7: =1126745 -> 1126745 | L7: -8619616 | M7: -74600618 | N7: -161998341 | O7: -739978000 | P7: -1812097 | Q7: -4342126
A8: Other operating income | I8: 197995 | J8: 361927 | K8: 612322
A9: Administration expenses | I9: -2924929 | J9: -3047099 | K9: -3558397
A10: Operating profit | H10: -936437 | I10: =SUM(I6:I9) -> -1354722 | J10: =SUM(J6:J9) -> -2685172 | K10: =SUM(K6:K9) -> -2946075 | L10: =SUM(L6:L9) -> 11596451 | M10: =SUM(M6:M9) -> 402731168 | N10: =SUM(N6:N9) -> 1567387720 | O10: =SUM(O6:O9) -> 4663423000 | P10: =SUM(P6:P9) -> 12367050 | Q10: =SUM(Q6:Q9) -> 8237104
A11: Share of profit from joint venture | I11: 12715 | J11: 22687
A12: Fair value adjustments | H12: =-25000 -> -25000 | I12: =-347807 -> -347807 | K12: 40500 | M12: 164798251 | N12: 43635647 | O12: 1321803000 | P12: 4570270 | Q12: 2200
A13: Net interest paid | L13: -1070216 | M13: -4265353 | N13: -12987289 | O13: -338789000 | P13: -245616 | Q13: -363607
A14: Net monetory loss | M14: -226574135 | N14: -1017558893 | O14: -996715000 | P14: -3403309
A15: Interest received | I15: 4438 | J15: 86302
A16: Finance costs | H16: -344253 | I16: -82569 | J16: -39621 | K16: -117448
A17: Income Before Tax (EBT) | H17: =SUM(H10:H16) -> -1305690 | I17: =SUM(I10:I16) -> -1767945 | J17: =SUM(J10:J16) -> -2615804 | K17: =SUM(K10:K16) -> -3023023 | L17: =SUM(L10:L16) -> 10526235 | M17: =SUM(M10:M16) -> 336689931 | N17: =SUM(N10:N16) -> 580477185 | O17: =SUM(O10:O16) -> 4649722000 | ... Q17: =SUM(Q10:Q16) -> 7875697
A18: Tax | H18: 272386 | I18: 932984 | J18: -189038 | K18: -475431 | L18: -1358850 | M18: -182858718 | N18: -54238841 | O18: -1263263000 | P18: -887680 | Q18: -325225
A19: Profit from continuing operations | H19: =H17+H18 -> -1033304 | I19: =I17+I18 -> -834961 | J19: =J17+J18 -> -2804842 | K19: =K17+K18 -> -3498454 | L19: =L17+L18 -> 9167385 | M19: =M17+M18 -> 153831213 | N19: =N17+N18 -> 526238344 | O19: =O17+O18 -> 3386459000 | ... Q19: =Q17+Q18 -> 7550472 | S19: =Q19/Q3 -> 0.1402547
A20: Profit from discontinued operations | H20: 455881 | I20: 203403
A21: Profit for the year | H21: =SUM(H19:H20) -> -577423 | I21: =SUM(I19:I20) -> -631558 | J21: =SUM(J19:J20) -> -2804842 | K21: =SUM(K19:K20) -> -3498454 | L21: =SUM(L19:L20) -> 9167385 | M21: =SUM(M19:M20) -> 153831213 | N21: =SUM(N19:N20) -> 526238344 | O21: =SUM(O19:O20) -> 3386459000 | ... Q21: =SUM(Q19:Q20) -> 7550472
A22: Other comprehensive income | I22: 520318 | J22: 610729 | K22: 1077972 | L22: 10354583 | M22: 40747176
A23: Total comprehensive income | I23: =I21+I22 -> -111240 | J23: =J21+J22 -> -2194113 | K23: =K21+K22 -> -2420482 | L23: =L21+L22 -> 19521968 | M23: =M21+M22 -> 194578389 | N23: =N21+N22 -> 526238344 | O23: =O21+O22 -> 3386459000 | P23: =P21+P22 -> 12400715 | Q23: =Q21+Q22 -> 7550472
A25: Basic income attributable to owners of parent | H25: =H27-H26 -> -1033304 | I25: =I27-I26 -> -834961 | J25: =J27-J26 -> -2804842 | K25: =K27-K26 -> -3498454 | L25: =L27-L26 -> 9167385 | M25: =M27-M26 -> 153831213 | N25: =N27-N26 -> 526238344 | O25: =O27-O26 -> 3386459000 | ... Q25: =Q27-Q26 -> 7550472
A26: Non controlling interests
A27: Income attributable to shareholders | H27: =H19 -> -1033304 | I27: =I19 -> -834961 | J27: =J19 -> -2804842 | K27: =K19 -> -3498454 | L27: =L19 -> 9167385 | M27: =M19 -> 153831213 | N27: =N19 -> 526238344 | O27: =O19 -> 3386459000 | ... Q27: =Q19 -> 7550472
A29: Basic income attributable to owners of parent
A30: Comprehensive income attributable to owners of parent | H30: =H32-H31 -> -577423 | I30: =I32-I31 -> -111240 | J30: =J32-J31 -> -2194113 | K30: =K32-K31 -> -2420482 | L30: =L32-L31 -> 19521968 | M30: =M32-M31 -> 194578389 | N30: =N32-N31 -> 526238344 | O30: =O32-O31 -> 3386459000 | ... Q30: =Q32-Q31 -> 7550472
A31: Non controlling interests
A32: Income attributable to shareholders | H32: =H21+H22 -> -577423 | I32: =I23 -> -111240 | J32: =J23 -> -2194113 | K32: =K23 -> -2420482 | L32: =L23 -> 19521968 | M32: =M23 -> 194578389 | N32: =N23 -> 526238344 | O32: =O23 -> 3386459000 | P32: =P23 -> 12400715 | Q32: =Q23 -> 7550472
A34: Basic Earnings per share | H34: =H25/H131*100 -> #DIV/0! | I34: =I25/I131*100 -> -0.37867788 | J34: =J25/J131*100 -> -1.2720733 | K34: =K30/K131*100 -> -1.0432218 | L34: =L30/L131*100 -> 8.3719734 | M34: =M30/M131*100 -> 80.519513 | N34: =N30/N131*100 -> 217.76548 | O34: =O30/O131*100 -> 1401.3685 | P34: =P30/P131*100 -> 5.1316055 | Q34: =Q30/Q131*100 -> 3.1540465
A35: Headline earnings per share | L35: 3.86 | M35: 11.81 | N35: 11.81 | O35: 11.81 | P35: =P30/P131*100 -> 5.1316055 | Q35: =Q30/Q131*100 -> 3.1540465
A36: Diluted earnings per share | H36: =H30/H131*100 -> #DIV/0! | I36: =I30/I131*100 -> -0.050450414 | J36: =J30/J131*100 -> -0.99509087 | K36: =K30/K131*100 -> -1.0432218 | L36: =L30/L131*100 -> 8.3719734 | M36: =M30/M131*100 -> 80.519513 | N36: =N30/N131*100 -> 217.76548 | O36: =O30/O131*100 -> 1401.3685 | ... Q36: =Q30/Q131*100 -> 3.1540465
A37: Dividends
A38: http://www.aranca.com/about-aranca
A39: Tax rate | H39: =-I18/H17 -> 0.71455246 | I39: =-I18/I17 -> 0.5277223 | J39: =-J18/J17 -> -0.072267647 | K39: =-K18/K17 -> -0.15727006 | L39: =-L18/L17 -> 0.12909174 | M39: =-M18/M17 -> 0.54310718 | N39: =-N18/N17 -> 0.093438368 | O39: =-O18/O17 -> 0.27168571 | P39: =-P18/P17 -> 0.066801145 | Q39: =-Q18/Q17 -> 0.041294758
A40: BALANCE SHEET | H40: =H1 -> Dec | I40: =I1 -> Dec | J40: =J1 -> Dec | K40: =K1 -> Dec | L40: =L1 -> Dec | M40: =M1 -> Dec | N40: =N1 -> Dec | O40: =O1 -> Dec | ... Q40: =Q1 -> Dec
H41: =H2 -> 2014 | I41: =I2 -> 2015 | J41: =J2 -> 2016 | K41: =K2 -> 2017 | L41: =L2 -> 2018 | M41: 2019 | N41: 2020 | O41: 2021 | P41: 2022 | Q41: 2023
A42: PPE | H42: 11792693 | I42: 6004892 | J42: 6731970 | K42: 8727868 | L42: 53986552 | M42: 757571799 | N42: 1578414353 | O42: 7410742000 | P42: 19944208 | Q42: 23630406
A43: Deferred tax asset
A44: Investment in Property | H44: 4757307 | I44: 4485500 | J44: 4467500 | K44: 4616000 | L44: 28672278 | M44: 293417950 | N44: 648896890 | O44: 4920298000 | P44: 9802065 | Q44: 7800930
A45: Intangible asset
A46: Investments | H46: 504 | I46: 678982 | J46: 1318567 | K46: 2146260 | L46: 17365368 | M46: 53629893 | N46: 260774263 | O46: 513456000 | P46: 215051 | Q46: 78304
A47: Total Non current Assets | H47: =SUM(H42:H46) -> 16550504 | I47: =SUM(I42:I46) -> 11169374 | J47: =SUM(J42:J46) -> 12518037 | K47: =SUM(K42:K46) -> 15490128 | L47: =SUM(L42:L46) -> 100024198 | M47: =SUM(M42:M46) -> 1104619642 | N47: =SUM(N42:N46) -> 2488085506 | O47: =SUM(O42:O46) -> 12844496000 | ... Q47: =SUM(Q42:Q46) -> 31509640 | S47: =SUM(S42:S46) -> 0 | T47: =SUM(T42:T46) -> 0 | U47: =SUM(U42:U46) -> 0
A48: Current Assets
A49: Inventories | H49: 5365107 | I49: 400472 | J49: 954819 | K49: 1200575 | L49: 10720948 | M49: 128694039 | N49: 189327333 | O49: 638045000 | P49: 507804 | Q49: 4580974
A50: Prepayment and deposits
A51: Trade and other receivables | I51: 1957829 | J51: 3579559 | K51: 5372084
A52: Contracts in progress and contracts receivables | H52: 10271933 | I52: 5095397 | J52: 6545933 | K52: 9734620 | L52: 126450215 | M52: 773546605 | N52: 4394659753 | O52: 19667116000 | P52: 31279656 | Q52: 46962352
A53: Short term investments | I53: 1620000
A54: Tax Assets | H54: 52498 | I54: 63708 | J54: 63802 | K54: 63802 | L54: 488093
A55: Cash and equivalents | H55: 1729139 | I55: 737173 | J55: 780267 | K55: 1294967 | L55: 23534630 | M55: 53049371 | N55: 382425791 | O55: 6048304000 | P55: 1538014 | Q55: 2731700
A56: Assets classified as held for sale
A57: Loans
A58: Total Current Assets | H58: =SUM(H49:H57) -> 17418677 | I58: =SUM(I49:I57) -> 9874579 | J58: =SUM(J49:J57) -> 11924380 | K58: =SUM(K49:K57) -> 17666048 | L58: =SUM(L49:L57) -> 161193886 | M58: =SUM(M49:M57) -> 955290015 | N58: =SUM(N49:N57) -> 4966412877 | O58: =SUM(O49:O57) -> 26353465000 | ... Q58: =SUM(Q49:Q57) -> 54275026
A59: Assets in disposal group as held for sale
A60: Total Assets | H60: =H58+H47 -> 33969181 | I60: =I58+I47 -> 21043953 | J60: =J58+J47 -> 24442417 | K60: =K58+K47 -> 33156176 | L60: =L58+L47 -> 261218084 | M60: =M58+M47 -> 2059909657 | N60: =N58+N47 -> 7454498383 | O60: =O58+O47 -> 39197961000 | ... Q60: =Q58+Q47 -> 85784666
A61: Equity and Liabilities
A62: Share Capital | H62: 2204937 | I62: 2204937 | J62: 2204937 | K62: 2320199 | L62: 14484122 | M62: 65365057 | N62: 105067494 | O62: 361180000 | P62: 2338831 | Q62: 2316175
A63: Share Premium | H63: 260063 | I63: 260063 | J63: 260063 | K63: 402987 | L63: 2518315 | M63: 24603941 | N63: 39548262 | O63: 135951000 | P63: 455177 | Q63: 455177
A64: Non distributable reserve | H64: 17647053 | I64: 8106081 | J64: 8396930 | K64: 9475558 | L64: 56360795 | M64: 811142938 | N64: 1583471993 | O64: 4910879000 | P64: 8347992 | Q64: 7426896
A65: Revaluation reserve
A66: Foreign currency translation reserve
A67: Equity component of shareholders loans | I67: 1219581 | J67: 1449613
A68: Retained earnings | K68: 1839661 | L68: 29432341 | M68: 261617989 | N68: 946761905 | O68: 6142061000 | P68: 18782703 | Q68: 14028887
A69: Equity attributable to equity holders of the parent | H69: =SUM(H62:H68) -> 20112053 | I69: =SUM(I62:I68) -> 11790662 | J69: =SUM(J62:J68) -> 12311543 | K69: =SUM(K62:K68) -> 14038405 | L69: =SUM(L62:L68) -> 102795573 | M69: =SUM(M62:M68) -> 1162729925 | N69: =SUM(N62:N68) -> 2674849654 | O69: =SUM(O62:O68) -> 11550071000 | ... Y69: =SUM(Y62:Y68) -> 0
A70: Non-controlling interest
A71: Total Equity | H71: =H69+H70 -> 20112053 | I71: =I69+I70 -> 11790662 | J71: =J69+J70 -> 12311543 | K71: =K69+K70 -> 14038405 | L71: =L69+L70 -> 102795573 | M71: =M69+M70 -> 1162729925 | N71: =N69+N70 -> 2674849654 | O71: =O69+O70 -> 11550071000 | ... Q71: =Q69+Q70 -> 24227135
A73: Deferred tax liability | H73: 2406933 | I73: 1063765 | J73: 1250731 | K73: 1778972 | L73: 14363279 | M73: 247406937 | N73: 504115516 | O73: 3029134000 | P73: 7556664 | Q73: 7861646
A74: Long term payable
A75: Finance lease liabilities | K75: 499130 | L75: 2575946 | M75: 1123366
A76: Interest bearing borrowings | H76: 416667 | I76: 222268 | J76: 315567 | K76: 910000 | L76: 1242300 | M76: 10311067 | N76: 40379961
A77: Non current Liabilities | H77: =SUM(H73:H76) -> 2823600 | I77: =SUM(I73:I76) -> 1286033 | J77: =SUM(J73:J76) -> 1566298 | K77: =SUM(K73:K76) -> 3188102 | L77: =SUM(L73:L76) -> 18181525 | M77: =SUM(M73:M76) -> 258841370 | N77: =SUM(N73:N76) -> 544495477 | O77: =SUM(O73:O76) -> 3029134000 | ... Y77: =SUM(Y73:Y76) -> 0
A78: Current Liabilities
A79: Provisions
A80: Deferred consideration
A81: Interest bearing borrowings | H81: 1166667 | I81: 222267 | J81: 390267 | K81: 205853 | L81: 4005528 | M81: 8896062 | N81: 167359291 | O81: 1138874000 | P81: 456160 | Q81: 1880547
A82: Trade and other payables | H82: 9866861 | I82: 4955445 | J82: 8125280 | K82: 13154104 | L82: 133049519 | M82: 628624856 | N82: 4067726978 | O82: 23479882000 | P82: 25349271 | Q82: 51815338
A83: Finance lease liabilities | K83: 284142 | L83: 3185939 | M83: 817444 | N83: 66983
A84: Subscontractors | I84: 2789546 | J84: 2049029 | K84: 2285570
A85: Liabilities directly associated with assets in disposal group
A86: Total Current liabilities | H86: =SUM(H78:H84) -> 11033528 | I86: =SUM(I78:I85) -> 7967258 | J86: =SUM(J79:J85) -> 10564576 | K86: =SUM(K79:K85) -> 15929669 | L86: =SUM(L78:L84) -> 140240986 | M86: =SUM(M78:M83) -> 638338362 | N86: =SUM(N78:N83) -> 4235153252 | O86: =SUM(O78:O83) -> 24618756000 | P86: =SUM(P78:P83) -> 25805431 | Q86: =SUM(Q78:Q83) -> 53695885 | R86: =SUM(R78:R83) -> 0 | S86: =SUM(S78:S83) -> 0 | T86: =SUM(T78:T83) -> 0 | ... W86: =SUM(W78:W83) -> 0
A87: Total Liabilities | H87: =H86+H77 -> 13857128 | I87: =I86+I77 -> 9253291 | J87: =J86+J77 -> 12130874 | K87: =K86+K77 -> 19117771 | L87: =L86+L77 -> 158422511 | M87: =M86+M77 -> 897179732 | N87: =N86+N77 -> 4779648729 | O87: =O86+O77 -> 27647890000 | ... AC87: =AC86+AC77 -> 0
A88: TOTAL LIABILITIES and EQUITY | H88: =H87+H71 -> 33969181 | I88: =I87+I71 -> 21043953 | J88: =J87+J71 -> 24442417 | K88: =K87+K71 -> 33156176 | L88: =L87+L71 -> 261218084 | M88: =M87+M71 -> 2059909657 | N88: =N87+N71 -> 7454498383 | O88: =O87+O71 -> 39197961000 | ... Q88: =Q87+Q71 -> 85784666
A90: CASH FLOW | H90: =H40 -> Dec | I90: Dec | J90: Dec | K90: Dec | L90: Dec | M90: Dec | N90: Dec | O90: Dec | P90: Dec | Q90: Dec
H91: 2014 | I91: 2015 | J91: 2016 | K91: 2017 | L91: 2018 | M91: 2019F | N91: 2020 | O91: 2021 | P91: 2021 | Q91: 2021
A92: Cash generated from operations | H92: 1969797 | I92: 1633461 | J92: 553165 | K92: 2383250 | L92: 20072981 | M92: 589696298 | N92: 615874311 | O92: 8721813000 | P92: 771971 | Q92: 4978645
A93: Dividend paid
A94: Finance cost | I94: -78131 | J94: 46681 | K94: -117448
A95: net cash generated from discontinued operations | I95: 452967
A96: Income tax paid | I96: -38500 | J96: -8335
A97: Net cashflow from operating activities | H97: =SUM(H92:H96) -> 1969797 | I97: =SUM(I92:I96) -> 1969797 | J97: =SUM(J92:J96) -> 591511 | K97: =SUM(K92:K96) -> 2265802 | L97: =SUM(L92:L96) -> 20072981 | M97: =SUM(M92:M96) -> 589696298 | N97: =SUM(N92:N96) -> 615874311 | O97: =SUM(O92:O96) -> 8721813000 | P97: =P92 -> 771971 | Q97: =Q92 -> 4978645
A98: net cash generated from investing activities | L98: -1633551 | M98: -589737378 | N98: -492532971 | O98: -3936732000 | P98: -4746695 | Q98: -4150995
A99: Purchase of PPE to expand operations | I99: -210896 | J99: -1972227 | K99: -2983430
A100: Purchase of shares
A101: acquisition of short term investments
A102: Additions of intangible assets
A103: Disposal of investment property | J103: 20000 | K103: 5699
A104: Purchase of Tbills | I104: -1620000
A105: Proceeds on disposal of PPE | I105: 75310 | J105: 207023 | K105: 63207
...

Sheet DCF
L2: (Interim) | M2: Year 1 | N2: Year 2-10 | O2: Beyond 10
A3: Fiscal Year | B3: 2013 | C3: 2015 | D3: 2016 | E3: 2017 | F3: 2018 | G3: 2019 | H3: 2020 | I3: 2021 | J3: 2022 | K3: 2023
A5: Sales | B5: =(K5/C5)^(1/5)-1 -> 0.3991636 | C5: ='Financials FY'!I3 -> 10039549 | D5: ='Financials FY'!J3 -> 19139918 | E5: ='Financials FY'!K3 -> 27451196 | F5: ='Financials FY'!L3 -> 248549590 | G5: ='Financials FY'!M3 -> 1498657461 | H5: ='Financials FY'!N3 -> 8390738256 | I5: ='Financials FY'!O3 -> 25284481000 | J5: ='Financials FY'!P3 -> 49818414 | K5: ='Financials FY'!Q3 -> 53834005 | L5: ='Financials HY'!I3 -> 31510454 | M5: =K5*(1+M6) -> 57112496
A6: Sales growth | D6: =(D5-C5)/C5 -> 0.90645197 | E6: =(E5-D5)/D5 -> 0.43423791 | F6: =(F5-E5)/E5 -> 8.0542354 | G6: =(G5-F5)/F5 -> 5.0296115 | H6: =(H5-G5)/G5 -> 4.5988366 | I6: =(I5-H5)/H5 -> 2.0133798 | J6: =(J5-I5)/I5 -> -0.99802968 | K6: =(K5-J5)/J5 -> 0.080604553 | L6: =('Financials HY'!I3-'Financials HY'!H3)/'Financials HY'!H3 -> 0.30483792 | M6: =(1+Q6)*(1+Q7)-1 -> 0.0609 | N6: 0.08 | O6: 0.07 | P6: Inflation | Q6: 0.03
A7: EBIT | C7: ='Financials FY'!I10 -> -1354722 | D7: ='Financials FY'!J10 -> -2685172 | E7: ='Financials FY'!K10 -> -2946075 | F7: ='Financials FY'!L10 -> 11596451 | G7: ='Financials FY'!M10 -> 402731168 | H7: ='Financials FY'!N10 -> 1567387720 | I7: ='Financials FY'!O10 -> 4663423000 | J7: ='Financials FY'!P10 -> 12367050 | K7: ='Financials FY'!Q10 -> 8237104 | L7: ='Financials HY'!I13 -> 5036750 | P7: order book | Q7: 0.03
A8: EBIT Margin | C8: =C7/C5 -> -0.13493853 | D8: =D7/D5 -> -0.14029172 | E8: =E7/E5 -> -0.10732046 | F8: =F7/F5 -> 0.046656488 | G8: =G7/G5 -> 0.26872796 | H8: =H7/H5 -> 0.18679974 | I8: =I7/I5 -> 0.18443815 | J8: =J7/J5 -> 0.24824255 | ... L8: =L7/L5 -> 0.15984378 | M8: 0.15 | N8: 0.15 | O8: 0.15
A9: Invested Capital | B9: =(K9/C9)^(1/5)-1 -> 0.15246921 | C9: ='Financials FY'!I138 -> 11498024 | D9: ='Financials FY'!J138 -> 12237110 | E9: ='Financials FY'!K138 -> 14143433 | F9: ='Financials FY'!L138 -> 87694710 | G9: ='Financials FY'!M138 -> 1129705127 | H9: ='Financials FY'!N138 -> 2500230098 | I9: ='Financials FY'!O138 -> 6640641000 | J9: ='Financials FY'!P138 -> 28842849 | K9: ='Financials FY'!Q138 -> 23375982
A10: Sales/Capital | B10: =AVERAGE(C10:D10) -> 1.2186212 | C10: =C5/C9 -> 0.87315429 | D10: =D5/D9 -> 1.5640881 | E10: =E5/E9 -> 1.9409146 | F10: =F5/F9 -> 2.8342598 | G10: =G5/G9 -> 1.3265917 | H10: =H5/H9 -> 3.3559864 | I10: =I5/I9 -> 3.8075362 | J10: =J5/J9 -> 1.7272362 | K10: =K5/K9 -> 2.3029623 | M10: 0.05 | N10: 0.05 | O10: 0.05
A11: Return on Capital | C11: =C7*(1-'Financials FY'!I39)/C9 -> -0.055644778 | D11: =D7*(1-'Financials FY'!J39)/D9 -> -0.2352862 | E11: =E7*(1-'Financials FY'!K39)/E9 -> -0.24105918 | F11: =F7*(1-'Financials FY'!L39)/F9 -> 0.11516595 | G11: =G7*(1-'Financials FY'!M39)/G9 -> 0.16287877 | H11: =H7*(1-'Financials FY'!N39)/H9 -> 0.56832112 | I11: =I7*(1-'Financials FY'!O39)/I9 -> 0.51146232 | J11: =J7*(1-'Financials FY'!P39)/J9 -> 0.40013096 | K11: =K7*(1-'Financials FY'!Q39)/K9 -> 0.33782345 | O11: 0.15
A12: Cost of Capital | M12: =WACC -> 0.13379251 | N12: 0.12 | O12: 0.12
A13: Ebit Growth | D13: =(D7-C7)/C7 -> 0.98208341 | E13: =(E7-D7)/D7 -> 0.097164353 | F13: =(F7-E7)/E7 -> -4.9362375 | G13: =(G7-F7)/F7 -> 33.728829 | H13: =(H7-G7)/G7 -> 2.8918957 | I13: =(I7-H7)/H7 -> 1.9752836 | J13: =(J7-I7)/I7 -> -0.99734807 | K13: =(K7-J7)/J7 -> -0.33394755
B15: 2023 | C15: 2024 | D15: 2025 | E15: 2026 | F15: 2027 | G15: 2028 | H15: 2029 | I15: 2030 | J15: 2031 | K15: 2032 | L15: Terminal year
A16: Revenue | B16: =M5 -> 57112496 | C16: =B16*(1+$N$6) -> 61681496 | D16: =C16*(1+$N$6) -> 66616015 | E16: =D16*(1+$N$6) -> 71945296 | F16: =E16*(1+$N$6) -> 77700920 | G16: =F16*(1+$N$6) -> 83916994 | H16: =G16*(1+$N$6) -> 90630353 | I16: =H16*(1+$N$6) -> 97880782 | J16: =I16*(1+$N$6) -> 1.0571124e+08 | K16: =J16*(1+$N$6) -> 1.1416814e+08 | L16: =K16*(1+$O$6) -> 1.2215991e+08
A17: EBIT | B17: =B16*M8 -> 8566874.4 | C17: =C16*$N$8 -> 9252224.3 | D17: =D16*$N$8 -> 9992402.3 | E17: =E16*$N$8 -> 10791794 | F17: =F16*$N$8 -> 11655138 | G17: =G16*$N$8 -> 12587549 | H17: =H16*$N$8 -> 13594553 | I17: =I16*$N$8 -> 14682117 | J17: =J16*$N$8 -> 15856687 | K17: =K16*$N$8 -> 17125222 | L17: =L16*$O$6 -> 8551194
A18: EBIT(1-t) | B18: =B17*(1-0.2475) -> 6446573 | C18: =C17*(1-0.2475) -> 6962298.8 | D18: =D17*(1-0.2475) -> 7519282.7 | E18: =E17*(1-0.2475) -> 8120825.3 | F18: =F17*(1-0.2475) -> 8770491.4 | G18: =G17*(1-0.2475) -> 9472130.7 | H18: =H17*(1-0.2475) -> 10229901 | I18: =I17*(1-0.2475) -> 11048293 | ... L18: =L17*(1-0.2475) -> 6434773.5
A19: Reinvestment | B19: =B16*M10 -> 2855624.8 | C19: =C16*$N$10 -> 3084074.8 | D19: =D16*$N$10 -> 3330800.8 | E19: =E16*$N$10 -> 3597264.8 | F19: =F16*$N$10 -> 3885046 | G19: =G16*$N$10 -> 4195849.7 | H19: =H16*$N$10 -> 4531517.7 | I19: =I16*$N$10 -> 4894039.1 | J19: =J16*$N$10 -> 5285562.2 | K19: =K16*$N$10 -> 5708407.2 | L19: =L16*O10 -> 6107995.7
A20: FCF | B20: =B18-B19 -> 3590948.2 | C20: =C18-C19 -> 3878224 | D20: =D18-D19 -> 4188482 | E20: =E18-E19 -> 4523560.5 | F20: =F18-F19 -> 4885445.4 | G20: =G18-G19 -> 5276281 | H20: =H18-H19 -> 5698383.5 | I20: =I18-I19 -> 6154254.1 | ... L20: =L18-L19 -> 326777.77
A21: Discount rate | B21: =1+M12 -> 1.1337925 | C21: =B21*(1+N12) -> 1.2698476 | D21: =C21*(1+$O$12) -> 1.4222293 | E21: =D21*(1+$O$12) -> 1.5928968 | F21: =E21*(1+$O$12) -> 1.7840445 | G21: =F21*(1+$O$12) -> 1.9981298 | H21: =G21*(1+$O$12) -> 2.2379054 | I21: =H21*(1+$O$12) -> 2.506454 | J21: =I21*(1+$O$12) -> 2.8072285 | K21: =J21*(1+$O$12) -> 3.1440959 | L21: =K21*(1+$O$12) -> 3.5213874
A22: Reinvestment rate | B22: =B19/B18 -> 0.44296788 | C22: =C19/C18 -> 0.44296788 | D22: =D19/D18 -> 0.44296788 | E22: =E19/E18 -> 0.44296788 | F22: =F19/F18 -> 0.44296788 | G22: =G19/G18 -> 0.44296788 | H22: =H19/H18 -> 0.44296788 | I22: =I19/I18 -> 0.44296788 | ... K22: =K19/K18 -> 0.44296788 | L22: =O6/L24 -> 0.77075775
A23: Invested Capital | B23: =K9+B19 -> 26231607 | C23: =B23+C19 -> 29315682 | D23: =C23+D19 -> 32646482 | E23: =D23+E19 -> 36243747 | F23: =E23+F19 -> 40128793 | G23: =F23+G19 -> 44324643 | H23: =G23+H19 -> 48856161 | I23: =H23+I19 -> 53750200 | J23: =I23+J19 -> 59035762 | ... L23: =K23+L19 -> 70852165
A24: ROIC | B24: =B18/B23 -> 0.24575593 | C24: =C18/C23 -> 0.23749401 | D24: =D18/D23 -> 0.23032444 | E24: =E18/E23 -> 0.22406142 | F24: =F18/F23 -> 0.21855856 | G24: =G18/G23 -> 0.21369897 | H24: =H18/H23 -> 0.20938815 | I24: =I18/I23 -> 0.20554888 | ... L24: =L18/L23 -> 0.090819716
L25: =L20/(O12-O6) -> 6535555.4
A26: FCF | B26: =B20/B21 -> 3167200.5 | C26: =C20/(1+C21) -> 1708583.4 | D26: =D20/(1+D21) -> 1729184.7 | E26: =E20/(1+E21) -> 1744597.2 | F26: =F20/(1+F21) -> 1754801.5 | G26: =G20/(1+G21) -> 1759857.4 | H26: =H20/(1+H21) -> 1759898.1 | I26: =I20/(1+I21) -> 1755121.9 | J26: =J20/(1+J21) -> 1745782.9 | K26: =K20/(1+K21) -> 1732180.5 | L26: =L25/L21 -> 1855960.3
A30: Calculation
A31: Terminal value | C31: =L26 -> 1855960.3
A32: Present Value | C32: =SUM(B26:K26) -> 18857208
A33: Excess Cash | C33: ='Financials HY'!I38 -> 2165459
A34: Investments | C34: ='Financials HY'!I29 -> 44688
A35: Interest Bearing Debt | C35: =-('Financials HY'!I64) -> -1265615
A36: Minority interest | C36: ='Financials HY'!D53 -> 0
A38: Present Value | C38: =SUM(C31:C36) -> 21657700
A39: Shares Outstanding | C39: 239390000 | F39: =28000000 -> 28000000
A40: Per Share Value Usc | C40: =C38/C39*100 -> 9.0470364 | F40: =F39/C39 -> 0.11696395
A41: Current Price Usc | C41: =298/25.28 -> 11.787975
A42: Margin of Safety | C42: =1-(C41/C40) -> -0.30296532 | F42: 16089596
F43: =300000000 -> 300000000
F44: =F42/F43 -> 0.053631987

Sheet WACC
B2: The standard procedure for estimating betas is to regress stock returns (Rj) against market returns (Rm) -
B4: Rj = a + b Rm
B5: where a is the intercept and b is the slope of the regression.
C6: or
B13: Damodaran Estimate of ERP | E13: 0.18
B14: Our estimate | E14: 0.14 | F14: A large part of Damodaran's estimate has to do with currency risk which does not fully apply for a domestic investor
B15: Re= rf+(rm-rf)*ß
B17: rm | C17: 0.15 | D17: market return
B18: Re | D18: required rate of return on equity/ cost of equity
B19: rf | C19: 0.18 | D19: risk free rate= usually refers to return you earn from investing in risk free instruments such as treasury bills
B20: rm-rf | C20: =C17-C19 -> -0.03 | D20: market risk premium
B21: ß | C21: 1 | D21: beta coefficient =unsystemic risk. Refers to the extent to which a stock reacts to the market as a whole
B23: Re | C23: =C19+(C20)*C21 -> 0.15
B27: Prevailing share price
B29: WACC=(E/V)*Re+D/V*Rd(1-Tc)
B31: Re | C31: 0.14 | D31: cost of equity
B32: Rd | C32: 0.1 | D32: cost of debt
B33: E | C33: ='Financials HY'!I75 -> 22232141 | D33: market value of the firm's equity
B34: D | C34: =-DCF!C35 -> 1265615 | D34: market value of the firm's debt
B35: V | C35: =C33+C34 -> 23497756 | D35: E+D
B36: Tc | C36: 0.2475 | D36: Corporate tax
B37: E/V | C37: =C33/C35 -> 0.9461389
B38: D/V | C38: =C34/C35 -> 0.053861101
B40: WACC | C40: =C37*C31+C38*(C32*C36) -> 0.13379251

Sheet Key Factors
A2: 1 | B2: Falling operational margins from 275 to 19%
A3: 2 | B3: $108m net cash position
A4: 3
A5: 4

Sheet Ratings
A2: STOCK RATING
A5: Strong Buy | B5: x>80
A6: Buy | B6: 80<x<65
A7: Hold | B7: 65<x<50 | D7: =D17 -> #DIV/0!
A8: Sell | B8: 50<x<35
A9: Strong Sell | B9: x<35
B12: Weighting | C12: Raw Score | D12: Weighted Score
A13: Valuation | B13: 0.6 | C13: =G41 -> 4.75 | D13: =C13*B13/10 -> 0.285
A14: Quality | B14: 0.2 | C14: =E85 -> #DIV/0! | D14: =C14*B14/10 -> #DIV/0!
A15: Growth | B15: 0.15 | C15: =E65 -> 2.65 | D15: =C15*B15/10 -> 0.03975
A16: Analyst Opinion | B16: 0.05 | C16: =C26 -> 6 | D16: =C16*B16/10 -> 0.03
A17: Total | B17: =SUM(B13:B16) -> 1 | C17: =SUM(C13:C16) -> #DIV/0! | D17: =SUM(D13:D16) -> #DIV/0!
E20: 0.8
E21: 0.65
A22: ANALYST OPINION (10) | B22: Max possible | C22: Score | E22: 0.5
A23: Above inflation pricing power for goods and services | B23: 10 | C23: 7 | E23: 0.35
A24: Earnings stability as shown by last 4years | B24: 10 | C24: 5
A25: Market sentiment on the company | B25: 10 | C25: 6
A26: Total | B26: =SUM(B23:B25) -> 30 | C26: =AVERAGE(C23:C25) -> 6
A32: VALUATION (40) | B32: Current price | C32: Estimated Price | D32: Differential | E32: Scoring | F32: Weighting | G32: Points
A33: DCF | B33: ='Data Input'!Q6 -> 11 | C33: ='Data Input'!Q5 -> 1.0869176 | D33: =(C33-B33)/B33 -> -0.90118931 | E33: =IF((D33>=50%),C45,IF(D33>=20%,C46,IF(D33>=10%,C47,IF(D33>=5%,C48,IF(D33>=0%,C49,IF(D33>=-5%,C50,IF(D33>=-15%,C51,IF(D33<=-15%,C52)))))))) -> 2 | F33: 0.6 | G33: =F33*E33 -> 1.2
A34: EBIT Valuation
B35: Current Valuation | C35: Fair Valuation / Industry average
A36: Price/NAV | B36: ='Data Input'!Q9 -> 1.0869176 | C36: 3 | D36: =(C36-B36)/B36 -> 1.7600988 | E36: =IF((D36>=50%),C45,IF(D36>=20%,C46,IF(D36>=10%,C47,IF(D36>=5%,C48,IF(D36>=0%,C49,IF(D36>=-5%,C50,IF(D36>=-15%,C51,IF(D36<=-15%,C52)))))))) -> 10 | F36: 0.1 | G36: =F36*E36 -> 1
A37: EV/EBIT | B37: ='Data Input'!Q10 -> 2.5897812 | C37: 5 | D37: =(C37-B37)/B37 -> 0.93066503 | E37: =IF((D37>=50%),C45,IF(D37>=20%,C46,IF(D37>=10%,C47,IF(D37>=5%,C48,IF(D37>=0%,C49,IF(D37>=-5%,C50,IF(D37>=-15%,C51,IF(D37<=-15%,C52)))))))) -> 10 | F37: 0.05 | G37: =F37*E37 -> 0.5
A38: P/E (F) | B38: ='Data Input'!Q8 -> 3.4875833 | C38: 30 | D38: =(C38-B38)/B38 -> 7.6019451 | E38: =IF((D38>=50%),C45,IF(D38>=20%,C46,IF(D38>=10%,C47,IF(D38>=5%,C48,IF(D38>=0%,C49,IF(D38>=-5%,C50,IF(D38>=-15%,C51,IF(D38<=-15%,C52)))))))) -> 10 | F38: 0.1 | G38: =F38*E38 -> 1
A39: P/E/P/E(F) | B39: ='Data Input'!Q7/'Data Input'!Q8 -> 1 | D39: =B39 -> 1 | E39: =IF((D39>=3),C45,IF(D39>=2,C46,IF(D39>=1.5,C47,IF(D39>=1,C48,IF(D39>=0.8,C49,IF(D39>=5,C50,IF(D39>=0.2,C51,IF(D39<=-1,C52)))))))) -> 7 | F39: 0.15 | G39: =F39*E39 -> 1.05
A41: Total | F41: =SUM(F33:F40) -> 1 | G41: =SUM(G33:G40) -> 4.75
A44: Margin of Safety | B44: Valuation Differential
B45: >50% | C45: 10
B46: 20%<x<50% | C46: 9
B47: 10%<x<20% | C47: 8
B48: 5%<x<10% | C48: 7
B49: 0%<x<5% | C49: 6
B50: 0%<x<-5% | C50: 4
B51: *-5%<x<-15% | C51: 3
B52: *-15%>x | C52: 2
A55: GROWTH (20) | B55: Relative Weighting | C55: Growth % | D55: Scoring | E55: Weighted Scoring
A56: Net profit growth | B56: 0.25 | C56: ='Data Input'!Q12 -> -0.95091717 | D56: =IF((C56>=50%),H56,IF(C56>=20%,H57,IF(C56>=10%,H58,IF(C56>=5%,H59,IF(C56>=0%,H60,IF(C56>=-5%,H61,IF(C56>=-15%,H62,IF(C56<=-15%,H63)))))))) -> 2 | E56: =D56*B56 -> 0.5 | G56: >50% | H56: 10
A57: Net profit growth (F) | B57: 0.1 | C57: ='Data Input'!Q13 -> 0 | D57: =IF((C57>=50%),H56,IF(C57>=20%,H57,IF(C57>=10%,H58,IF(C57>=5%,H59,IF(C57>=0%,H60,IF(C57>=-5%,H61,IF(C57>=-15%,H62,IF(C57<=-15%,H63)))))))) -> 6 | E57: =D57*B57 -> 0.6 | G57: 20%<x<50% | H57: 9
A58: Cash generated from operations growth | B58: 0.2 | C58: ='Data Input'!Q14 -> -0.99155727 | D58: =IF((C58>=50%),H56,IF(C58>=20%,H57,IF(C58>=10%,H58,IF(C58>=5%,H59,IF(C58>=0%,H60,IF(C58>=-5%,H61,IF(C58>=-15%,H62,IF(C58<=-15%,H63)))))))) -> 2 | E58: =D58*B58 -> 0.4 | G58: 10%<x<20% | H58: 8
A59: Cash generated from operations growth (F) | E59: =D59*B59 -> 0 | G59: 5%<x<10% | H59: 7
A60: Revenue growth | B60: 0.2 | C60: ='Data Input'!Q16 -> -0.96407851 | D60: =IF((C60>=50%),H56,IF(C60>=20%,H57,IF(C60>=10%,H58,IF(C60>=5%,H59,IF(C60>=0%,H60,IF(C60>=-5%,H61,IF(C60>=-15%,H62,IF(C60<=-15%,H63)))))))) -> 2 | E60: =D60*B60 -> 0.4 | G60: 0%<x<5% | H60: 6
A61: Revenue growth (F) | B61: 0.05 | C61: ='Data Input'!Q17 -> 0.0609 | D61: =IF((C61>=50%),H56,IF(C61>=20%,H57,IF(C61>=10%,H58,IF(C61>=5%,H59,IF(C61>=0%,H60,IF(C61>=-5%,H61,IF(C61>=-15%,H62,IF(C61<=-15%,H63)))))))) -> 7 | E61: =D61*B61 -> 0.35 | G61: 0%<x<-5% | H61: 4
A62: EBIT growth | B62: 0.1 | C62: ='Data Input'!Q19 -> -0.99823368 | D62: =IF((C62>=50%),H56,IF(C62>=20%,H57,IF(C62>=10%,H58,IF(C62>=5%,H59,IF(C62>=0%,H60,IF(C62>=-5%,H61,IF(C62>=-15%,H62,IF(C62<=-15%,H63)))))))) -> 2 | E62: =D62*B62 -> 0.2 | G62: *-5%<x<-15% | H62: 3
G63: *-15%>x | H63: 2
A64: Free cash flow growth | B64: 0.1 | C64: ='Data Input'!Q21 -> -21.147274 | D64: =IF((C64>=50%),H56,IF(C64>=20%,H57,IF(C64>=10%,H58,IF(C64>=5%,H59,IF(C64>=0%,H60,IF(C64>=-5%,H61,IF(C64>=-15%,H62,IF(C64<=-15%,H63)))))))) -> 2 | E64: =D64*B64 -> 0.2
A65: Total | B65: =SUM(B56:B64) -> 1 | E65: =SUM(E56:E64) -> 2.65
A69: QUALITY (30) | B69: Relative Weighting | C69: Metric | D69: Scoring | E69: Weighted Scoring
A70: ROE | B70: 0.1 | C70: ='Data Input'!Q25 -> 0.31165352 | D70: =IF((C70>=25%),L94,IF(C70>=20%,L95,IF(C70>=15%,L96,IF(C70>=10%,L97,IF(C70>=5%,L98,IF(C70>=0%,L99,IF(C70<=0%,L100))))))) -> 10 | E70: =D70*B70 -> 1
A71: ROA | B71: 0.05 | C71: ='Data Input'!Q26 -> 0.092055552 | D71: =IF((C71>=25%),L94,IF(C71>=20%,L95,IF(C71>=15%,L96,IF(C71>=10%,L97,IF(C71>=5%,L98,IF(C71>=0%,L99,IF(C71<=0%,L100))))))) -> 6 | E71: =D71*B71 -> 0.3
A72: ROIC | B72: 0.1 | C72: ='Data Input'!Q27 -> 0.33782345 | D72: =IF((C72>=20%),I80,IF(C72>=15%,I81,IF(C72>=10%,I82,IF(C72>=5%,I83,IF(C72>=0%,I84,IF(C72>=-5%,I85,IF(C72>=-15%,I86,IF(C72<=-15%,I87)))))))) -> 10 | E72: =D72*B72 -> 1
A73: Net Profit margin | B73: 0.1 | C73: ='Data Input'!Q28 -> 0.1402547 | D73: =IF((C73>=20%),O94,IF(C73>=15%,O95,IF(C73>=10%,O96,IF(C73>=5%,O97,IF(C73>=0%,O98,IF(C73>=-5%,O99,IF(C73<=-5%,O100))))))) -> 8 | E73: =D73*B73 -> 0.8
A74: Management | B74: 0.15 | D74: =D139 -> 8 | E74: =D74*B74 -> 1.2
A75: Receivables turnover % change | B75: 0.05 | C75: ='Data Input'!Q30 -> #DIV/0! | D75: =IF((C75>=20%),I80,IF(C75>=15%,I81,IF(C75>=10%,I82,IF(C75>=5%,I83,IF(C75>=0%,I84,IF(C75>=-5%,I85,IF(C75>=-15%,I86,IF(C75<=-15%,I87)))))))) -> #DIV/0! | E75: =D75*B75 -> #DIV/0!
A76: Inventory turnover % change | B76: 0.05 | C76: ='Data Input'!Q31 -> -1 | D76: =IF((C76>=20%),I80,IF(C76>=15%,I81,IF(C76>=10%,I82,IF(C76>=5%,I83,IF(C76>=0%,I84,IF(C76>=-5%,I85,IF(C76>=-15%,I86,IF(C76<=-15%,I87)))))))) -> 2 | E76: =D76*B76 -> 0.1
A77: Debt ratio | B77: 0.05 | C77: ='Data Input'!Q32 -> 0.021921715 | D77: =IF((C77>=25%),C111,IF(C77>=20%,C110,IF(C77>=15%,C109,IF(C77>=10%,C108,IF(C77>=5%,C107,IF(C77>0%,C106,IF(C77=0%,C105))))))) -> 9 | E77: =D77*B77 -> 0.45
A78: Total Asset Turnover % change | B78: 0.05 | C78: ='Data Input'!Q33 -> 0.50234645 | D78: =IF((C78>=20%),I80,IF(C78>=15%,I81,IF(C78>=10%,I82,IF(C78>=5%,I83,IF(C78>=0%,I84,IF(C78>=-5%,I85,IF(C78>=-15%,I86,IF(C78<=-15%,I87)))))))) -> 10 | E78: =D78*B78 -> 0.5
A79: Interest Cover ratio | B79: 0.05 | C79: ='Data Input'!Q34 -> 22.653865 | D79: =IF((C79>=10),F105,IF(C79>=5,F106,IF(C79>=3,F107,IF(C79>=2,F108,IF(C79>=1,F109,IF(C79>=0.5,F110,IF(C79<=0.5,F111))))))) -> 10 | E79: =D79*B79 -> 0.5
A80: ST % of current assets | B80: 0.05 | C80: ='Data Input'!Q35 -> 0.034648477 | D80: =IF((C73>=25%),F99,IF(C73>=20%,F98,IF(C73>=15%,F97,IF(C73>=10%,F96,IF(C73>=5%,F95,IF(C73>0%,F94,IF(C73=0%,F93))))))) -> 7 | E80: =D80*B80 -> 0.35 | H80: >20% | I80: 10
A81: Gross Margin % change | B81: 0.05 | C81: ='Data Input'!Q38 -> 0 | D81: =IF((C81>=20%),I80,IF(C81>=15%,I81,IF(C81>=10%,I82,IF(C81>=5%,I83,IF(C81>=0%,I84,IF(C81>=-5%,I85,IF(C81>=-15%,I86,IF(C81<=-15%,I87)))))))) -> 6 | E81: =D81*B81 -> 0.3 | H81: 15%<x<20% | I81: 9
A82: Gross Profit/Total Assets % change | B82: 0.05 | C82: ='Data Input'!Q39 -> 4.7472463 | D82: =IF((C82>=20%),I80,IF(C82>=15%,I81,IF(C82>=10%,I82,IF(C82>=5%,I83,IF(C82>=0%,I84,IF(C82>=-5%,I85,IF(C82>=-15%,I86,IF(C82<=-15%,I87)))))))) -> 10 | E82: =D82*B82 -> 0.5 | H82: 10%<x<15% | I82: 8
A83: Current ratio | B83: 0.05 | C83: ='Data Input'!Q36 -> 1.0107856 | D83: =IF((C83=3),C94,IF(C83>=2.5,C95,IF(C83>=2,C96,IF(C83>=1.5,C97,IF(C83>=1,C98,IF(C83>=0.5,C99,IF(C83<=0.5,C100))))))) -> 6 | E83: =D83*B83 -> 0.3 | H83: 5%<x<10% | I83: 7
A84: FCF/Debt | B84: 0.05 | C84: ='Data Input'!Q37 -> 0.44011131 | D84: =IF((C84>=100%),I93,IF(C84>=50%,I94,IF(C84>=20%,I95,IF(C84>=10%,I96,IF(C84>=5%,I97,IF(C84>=0%,I98,IF(C84<0%,I99))))))) -> 8 | E84: =D84*B84 -> 0.4 | H84: 0%<x<5% | I84: 6
A85: Total | B85: =SUM(B70:B84) -> 1 | E85: =SUM(E70:E84) -> #DIV/0! | H85: 0%<x<-5% | I85: 4
E86: 10 | H86: *-5%<x<-15% | I86: 3
H87: *-15%>x | I87: 2
B91: Current Ratio | E91: ST % invested capital | H91: FCF/Debt | L91: ROE
L92: ROA | N92: Net Margin
E93: 0 | F93: 10 | H93: >100% | I93: 10
B94: >3 | C94: 10 | E94: 0<x<5% | F94: 9 | H94: 50%<x<100% | I94: 9 | K94: >25% | L94: 10 | N94: >20% | O94: 10
B95: 2,5<x<3 | C95: 9 | E95: 5%<x<10% | F95: 8 | H95: 20%<x<50% | I95: 8 | K95: 20%<x<25% | L95: 9 | N95: 15%<x<20% | O95: 9
B96: 2<x<2,5 | C96: 8 | E96: 10%<x<15% | F96: 7 | H96: 10%<x<20% | I96: 7 | K96: 15%<x<20% | L96: 8 | N96: 10%<x<15% | O96: 8
B97: 1,5<x<2 | C97: 7 | E97: 15%<x<20% | F97: 6 | H97: 5%<x<10% | I97: 6 | K97: 10%<x<15% | L97: 7 | N97: 5%<x<10% | O97: 7
B98: 1<x<1,5 | C98: 6 | E98: 20%<x<25% | F98: 5 | H98: 0%<x<5% | I98: 5 | K98: 5%<x<10% | L98: 6 | N98: 0%<x<5% | O98: 6
B99: 0,5<x<1 | C99: 4 | E99: 25%<x | F99: 3 | H99: <0% | I99: 3 | K99: *0%<x<5% | L99: 5 | N99: *-5%<x<0% | O99: 4
B100: <0,5 | C100: 3 | K100: <0% | L100: 3 | N100: x<-5% | O100: 3
B103: Debt ratio | E103: Interest cover ratio
B105: 0 | C105: 10 | E105: >10 | F105: 10
B106: 0<x<5% | C106: 9 | E106: 5<x<10 | F106: 9
B107: 5%<x<10% | C107: 8 | E107: 3<x<5 | F107: 8
B108: 10%<x<15% | C108: 7 | E108: 2<x<3 | F108: 7
B109: 15%<x<20% | C109: 6 | E109: 1<x<2 | F109: 6
B110: 20%<x<25% | C110: 5 | E110: 0,5<x1 | F110: 4
B111: 25%<x | C111: 3 | E111: x<0,5 | F111: 3
E114: Total Asset turnover
B115: Inventory turnover
E116: Rise by more than 30% | F116: 10
B117: Rise by more than 30% | C117: 10 | E117: Rise by 20-30% | F117: 9
B118: Rise by 20-30% | C118: 9 | E118: Rise by 10-20% | F118: 8
B119: Rise by 10-20% | C119: 8 | E119: Rise by 5-10% | F119: 7
B120: Rise by 5-10% | C120: 7 | E120: Rise by 0- 5% | F120: 6
B121: Rise by 0- 5% | C121: 6 | E121: Rise by -5%-0% | F121: 4
B122: Drop by less than 5%-10% | C122: 4 | E122: Rise by less than -5% | F122: 3
B123: Drop by less than 10% | C123: 3
B125: Receivables turnover
B127: Rise by more than 30% | C127: 10
B128: Rise by 20-30% | C128: 9
B129: Rise by 10-20% | C129: 8
B130: Rise by 5-10% | C130: 7
...

Sheet Notes
P3: Description | Q3: 1997 | R3: 2023
P4: Exchange rate 1997 | Q4: 6 | R4: 6000
P5: Mkt cap ZWL | Q5: =1000000000 -> 1000000000 | R5: 220003000000
P6: Mkt cap june usd | Q6: =Q5/6 -> 1.6666667e+08 | R6: 44000000
E7: 2022 order book: US$214 Million
E8: Share buy back approved in May 2020 | P8: Revenue 1997 ZWL | Q8: 515660000 | R8: =DCF!K5 -> 53834005
E9: in 2021 over 17% of the admin expenses were absorbed by Bank charges only | P9: Revenue usd | Q9: =Q8/6 -> 85943333 | R9: =R8/1000 -> 53834.005
E10: The company has 23 ongoing projects
E11: Top 3 directors collectively owned 98 million shares OUT OF 241.65 million outstanding shares, that’s 40%. | P11: Share price zwl | Q11: 24 | R11: 856.75
C12: Top shareholders | E12: 1 | F12: Zumbani Capital- 2 white guys | H12: 0.2827 | P12: Share price USD | Q12: =Q11/6 -> 4 | R12: =R11/6000 -> 0.14279167
E13: 4 | F13: Giona Capital- Malunga | H13: 0.0767
E14: 6 | F14: Amalgamated Africa- Paddy | H14: 0.0453
P15: Number of shares | Q15: =41566870 -> 41566870 | R15: =DCF!C39 -> 239390000
E16: Masimba is owened by Management | P16: %ge change | Q16: 0 | R16: =(R15-Q15)/Q15 -> 4.7591539
